{"ma": {"ticker": "APGE", "found": true, "last_close": 134.2, "last_date": "2026-07-21", "benchmark": "^GSPC", "market_s": true, "ticker_long": true, "ticker_short": true, "mas": [{"ma_type": "SMA", "ma_period": 10, "ma_value": 133.992, "distance_pct": 0.16}, {"ma_type": "SMA", "ma_period": 20, "ma_value": 133.4575, "distance_pct": 0.56}, {"ma_type": "SMA", "ma_period": 30, "ma_value": 121.0123, "distance_pct": 10.9}, {"ma_type": "SMA", "ma_period": 40, "ma_value": 111.348, "distance_pct": 20.52}, {"ma_type": "SMA", "ma_period": 50, "ma_value": 105.4488, "distance_pct": 27.27}, {"ma_type": "SMA", "ma_period": 60, "ma_value": 101.7695, "distance_pct": 31.87}, {"ma_type": "EMA", "ma_period": 10, "ma_value": 133.3896, "distance_pct": 0.61}, {"ma_type": "EMA", "ma_period": 21, "ma_value": 127.7623, "distance_pct": 5.04}, {"ma_type": "EMA", "ma_period": 30, "ma_value": 122.31, "distance_pct": 9.72}, {"ma_type": "EMA", "ma_period": 40, "ma_value": 117.0357, "distance_pct": 14.67}, {"ma_type": "EMA", "ma_period": 50, "ma_value": 112.6635, "distance_pct": 19.12}, {"ma_type": "EMA", "ma_period": 60, "ma_value": 109.0065, "distance_pct": 23.11}], "stats": {"L|SMA|10": [{"period": 2, "win_rate": 45.65, "avg_win": 4.67, "avg_loss": -3.05, "pl_ratio": 1.5292, "touch_count": 46}, {"period": 3, "win_rate": 69.57, "avg_win": 4.5, "avg_loss": -5.91, "pl_ratio": 0.7616, "touch_count": 46}, {"period": 5, "win_rate": 63.04, "avg_win": 8.61, "avg_loss": -7.26, "pl_ratio": 1.1856, "touch_count": 46}, {"period": 10, "win_rate": 58.7, "avg_win": 13.7, "avg_loss": -9.62, "pl_ratio": 1.4244, "touch_count": 46}, {"period": 20, "win_rate": 66.67, "avg_win": 17.72, "avg_loss": -12.09, "pl_ratio": 1.4661, "touch_count": 45}, {"period": 60, "win_rate": 56.41, "avg_win": 22.27, "avg_loss": -14.53, "pl_ratio": 1.5323, "touch_count": 39}, {"period": 126, "win_rate": 43.33, "avg_win": 27.08, "avg_loss": -28.31, "pl_ratio": 0.9568, "touch_count": 30}, {"period": 252, "win_rate": 17.39, "avg_win": 7.85, "avg_loss": -16.71, "pl_ratio": 0.4699, "touch_count": 23}], "S|SMA|10": [{"period": 2, "win_rate": 50.0, "avg_win": 4.12, "avg_loss": -2.65, "pl_ratio": 1.5543, "touch_count": 48}, {"period": 3, "win_rate": 64.58, "avg_win": 4.52, "avg_loss": -4.66, "pl_ratio": 0.9701, "touch_count": 48}, {"period": 5, "win_rate": 62.5, "avg_win": 8.84, "avg_loss": -6.31, "pl_ratio": 1.3996, "touch_count": 48}, {"period": 10, "win_rate": 58.33, "avg_win": 14.86, "avg_loss": -10.46, "pl_ratio": 1.4207, "touch_count": 48}, {"period": 20, "win_rate": 68.09, "avg_win": 20.5, "avg_loss": -13.85, "pl_ratio": 1.4806, "touch_count": 47}, {"period": 60, "win_rate": 56.82, "avg_win": 36.29, "avg_loss": -17.77, "pl_ratio": 2.0427, "touch_count": 44}, {"period": 126, "win_rate": 48.72, "avg_win": 50.01, "avg_loss": -25.72, "pl_ratio": 1.9447, "touch_count": 39}, {"period": 252, "win_rate": 40.0, "avg_win": 62.11, "avg_loss": -20.44, "pl_ratio": 3.0389, "touch_count": 30}], "L|SMA|20": [{"period": 2, "win_rate": 58.06, "avg_win": 4.13, "avg_loss": -3.33, "pl_ratio": 1.2407, "touch_count": 31}, {"period": 3, "win_rate": 54.84, "avg_win": 8.11, "avg_loss": -3.97, "pl_ratio": 2.0448, "touch_count": 31}, {"period": 5, "win_rate": 66.67, "avg_win": 9.25, "avg_loss": -5.7, "pl_ratio": 1.6237, "touch_count": 30}, {"period": 10, "win_rate": 63.33, "avg_win": 18.23, "avg_loss": -6.8, "pl_ratio": 2.6818, "touch_count": 30}, {"period": 20, "win_rate": 70.0, "avg_win": 23.27, "avg_loss": -13.04, "pl_ratio": 1.784, "touch_count": 30}, {"period": 60, "win_rate": 56.52, "avg_win": 21.91, "avg_loss": -14.96, "pl_ratio": 1.465, "touch_count": 23}, {"period": 126, "win_rate": 33.33, "avg_win": 33.72, "avg_loss": -28.03, "pl_ratio": 1.2031, "touch_count": 15}, {"period": 252, "win_rate": 23.08, "avg_win": 1.36, "avg_loss": -17.27, "pl_ratio": 0.0785, "touch_count": 13}], "S|SMA|20": [{"period": 2, "win_rate": 53.57, "avg_win": 3.78, "avg_loss": -4.08, "pl_ratio": 0.9256, "touch_count": 28}, {"period": 3, "win_rate": 42.86, "avg_win": 8.56, "avg_loss": -3.95, "pl_ratio": 2.1677, "touch_count": 28}, {"period": 5, "win_rate": 51.85, "avg_win": 10.43, "avg_loss": -6.32, "pl_ratio": 1.6497, "touch_count": 27}, {"period": 10, "win_rate": 55.56, "avg_win": 17.78, "avg_loss": -7.54, "pl_ratio": 2.3591, "touch_count": 27}, {"period": 20, "win_rate": 70.37, "avg_win": 26.67, "avg_loss": -13.23, "pl_ratio": 2.0159, "touch_count": 27}, {"period": 60, "win_rate": 60.87, "avg_win": 36.41, "avg_loss": -18.79, "pl_ratio": 1.9377, "touch_count": 23}, {"period": 126, "win_rate": 50.0, "avg_win": 63.35, "avg_loss": -28.39, "pl_ratio": 2.2313, "touch_count": 20}, {"period": 252, "win_rate": 46.67, "avg_win": 38.9, "avg_loss": -18.31, "pl_ratio": 2.1253, "touch_count": 15}], "L|SMA|30": [{"period": 2, "win_rate": 46.88, "avg_win": 5.47, "avg_loss": -3.49, "pl_ratio": 1.5673, "touch_count": 32}, {"period": 3, "win_rate": 56.25, "avg_win": 7.77, "avg_loss": -4.25, "pl_ratio": 1.827, "touch_count": 32}, {"period": 5, "win_rate": 68.75, "avg_win": 8.7, "avg_loss": -6.56, "pl_ratio": 1.327, "touch_count": 32}, {"period": 10, "win_rate": 62.5, "avg_win": 16.33, "avg_loss": -10.23, "pl_ratio": 1.5967, "touch_count": 32}, {"period": 20, "win_rate": 59.38, "avg_win": 26.8, "avg_loss": -14.7, "pl_ratio": 1.8232, "touch_count": 32}, {"period": 60, "win_rate": 45.83, "avg_win": 20.52, "avg_loss": -15.27, "pl_ratio": 1.3438, "touch_count": 24}, {"period": 126, "win_rate": 26.32, "avg_win": 35.29, "avg_loss": -24.13, "pl_ratio": 1.4628, "touch_count": 19}, {"period": 252, "win_rate": 23.53, "avg_win": 12.65, "avg_loss": -19.25, "pl_ratio": 0.657, "touch_count": 17}], "S|SMA|30": [{"period": 2, "win_rate": 64.0, "avg_win": 3.48, "avg_loss": -3.59, "pl_ratio": 0.9674, "touch_count": 25}, {"period": 3, "win_rate": 56.0, "avg_win": 8.05, "avg_loss": -3.41, "pl_ratio": 2.3572, "touch_count": 25}, {"period": 5, "win_rate": 68.0, "avg_win": 8.58, "avg_loss": -5.48, "pl_ratio": 1.5672, "touch_count": 25}, {"period": 10, "win_rate": 60.0, "avg_win": 15.83, "avg_loss": -9.14, "pl_ratio": 1.7307, "touch_count": 25}, {"period": 20, "win_rate": 64.0, "avg_win": 23.4, "avg_loss": -12.93, "pl_ratio": 1.8091, "touch_count": 25}, {"period": 60, "win_rate": 50.0, "avg_win": 21.0, "avg_loss": -13.41, "pl_ratio": 1.5658, "touch_count": 20}, {"period": 126, "win_rate": 36.84, "avg_win": 74.59, "avg_loss": -25.34, "pl_ratio": 2.9433, "touch_count": 19}, {"period": 252, "win_rate": 43.75, "avg_win": 52.82, "avg_loss": -19.96, "pl_ratio": 2.6463, "touch_count": 16}], "L|SMA|40": [{"period": 2, "win_rate": 47.37, "avg_win": 4.6, "avg_loss": -3.26, "pl_ratio": 1.4095, "touch_count": 19}, {"period": 3, "win_rate": 63.16, "avg_win": 3.57, "avg_loss": -6.4, "pl_ratio": 0.5576, "touch_count": 19}, {"period": 5, "win_rate": 63.16, "avg_win": 10.76, "avg_loss": -6.8, "pl_ratio": 1.5828, "touch_count": 19}, {"period": 10, "win_rate": 73.68, "avg_win": 14.22, "avg_loss": -12.45, "pl_ratio": 1.1426, "touch_count": 19}, {"period": 20, "win_rate": 63.16, "avg_win": 26.07, "avg_loss": -13.18, "pl_ratio": 1.9782, "touch_count": 19}, {"period": 60, "win_rate": 50.0, "avg_win": 19.6, "avg_loss": -27.24, "pl_ratio": 0.7195, "touch_count": 14}, {"period": 126, "win_rate": 0.0, "avg_win": 0.0, "avg_loss": -24.99, "pl_ratio": 0.0, "touch_count": 9}, {"period": 252, "win_rate": 44.44, "avg_win": 16.72, "avg_loss": -10.22, "pl_ratio": 1.6358, "touch_count": 9}], "S|SMA|40": [{"period": 2, "win_rate": 52.38, "avg_win": 5.2, "avg_loss": -5.54, "pl_ratio": 0.939, "touch_count": 21}, {"period": 3, "win_rate": 61.9, "avg_win": 9.12, "avg_loss": -7.54, "pl_ratio": 1.2099, "touch_count": 21}, {"period": 5, "win_rate": 61.9, "avg_win": 16.8, "avg_loss": -8.8, "pl_ratio": 1.9092, "touch_count": 21}, {"period": 10, "win_rate": 66.67, "avg_win": 14.36, "avg_loss": -13.49, "pl_ratio": 1.0646, "touch_count": 21}, {"period": 20, "win_rate": 57.14, "avg_win": 28.33, "avg_loss": -10.47, "pl_ratio": 2.7064, "touch_count": 21}, {"period": 60, "win_rate": 47.06, "avg_win": 33.22, "avg_loss": -23.15, "pl_ratio": 1.4349, "touch_count": 17}, {"period": 126, "win_rate": 52.94, "avg_win": 40.43, "avg_loss": -25.26, "pl_ratio": 1.6003, "touch_count": 17}, {"period": 252, "win_rate": 46.67, "avg_win": 77.92, "avg_loss": -18.25, "pl_ratio": 4.2698, "touch_count": 15}], "L|SMA|50": [{"period": 2, "win_rate": 52.63, "avg_win": 4.09, "avg_loss": -2.7, "pl_ratio": 1.5169, "touch_count": 19}, {"period": 3, "win_rate": 68.42, "avg_win": 4.52, "avg_loss": -3.9, "pl_ratio": 1.1579, "touch_count": 19}, {"period": 5, "win_rate": 63.16, "avg_win": 9.92, "avg_loss": -4.93, "pl_ratio": 2.0133, "touch_count": 19}, {"period": 10, "win_rate": 68.42, "avg_win": 13.97, "avg_loss": -6.98, "pl_ratio": 2.0033, "touch_count": 19}, {"period": 20, "win_rate": 68.42, "avg_win": 27.67, "avg_loss": -8.33, "pl_ratio": 3.3198, "touch_count": 19}, {"period": 60, "win_rate": 70.0, "avg_win": 18.91, "avg_loss": -29.32, "pl_ratio": 0.6451, "touch_count": 10}, {"period": 126, "win_rate": 0.0, "avg_win": 0.0, "avg_loss": -20.58, "pl_ratio": 0.0, "touch_count": 6}, {"period": 252, "win_rate": 50.0, "avg_win": 17.15, "avg_loss": -16.99, "pl_ratio": 1.0091, "touch_count": 6}], "S|SMA|50": [{"period": 2, "win_rate": 60.0, "avg_win": 3.98, "avg_loss": -6.72, "pl_ratio": 0.5927, "touch_count": 20}, {"period": 3, "win_rate": 50.0, "avg_win": 4.4, "avg_loss": -6.77, "pl_ratio": 0.6489, "touch_count": 20}, {"period": 5, "win_rate": 55.0, "avg_win": 10.69, "avg_loss": -8.23, "pl_ratio": 1.2989, "touch_count": 20}, {"period": 10, "win_rate": 65.0, "avg_win": 8.72, "avg_loss": -11.33, "pl_ratio": 0.7696, "touch_count": 20}, {"period": 20, "win_rate": 60.0, "avg_win": 23.24, "avg_loss": -8.36, "pl_ratio": 2.7793, "touch_count": 20}, {"period": 60, "win_rate": 73.33, "avg_win": 26.24, "avg_loss": -20.22, "pl_ratio": 1.2975, "touch_count": 15}, {"period": 126, "win_rate": 50.0, "avg_win": 46.3, "avg_loss": -15.85, "pl_ratio": 2.9203, "touch_count": 12}, {"period": 252, "win_rate": 60.0, "avg_win": 88.09, "avg_loss": -22.65, "pl_ratio": 3.8886, "touch_count": 10}], "L|SMA|60": [{"period": 2, "win_rate": 52.38, "avg_win": 4.69, "avg_loss": -3.32, "pl_ratio": 1.4124, "touch_count": 21}, {"period": 3, "win_rate": 80.95, "avg_win": 7.17, "avg_loss": -9.54, "pl_ratio": 0.7514, "touch_count": 21}, {"period": 5, "win_rate": 66.67, "avg_win": 9.49, "avg_loss": -8.87, "pl_ratio": 1.0697, "touch_count": 21}, {"period": 10, "win_rate": 47.62, "avg_win": 23.91, "avg_loss": -9.01, "pl_ratio": 2.6539, "touch_count": 21}, {"period": 20, "win_rate": 52.38, "avg_win": 30.29, "avg_loss": -13.93, "pl_ratio": 2.1741, "touch_count": 21}, {"period": 60, "win_rate": 46.67, "avg_win": 20.14, "avg_loss": -19.59, "pl_ratio": 1.0282, "touch_count": 15}, {"period": 126, "win_rate": 36.36, "avg_win": 8.84, "avg_loss": -18.93, "pl_ratio": 0.4669, "touch_count": 11}, {"period": 252, "win_rate": 27.27, "avg_win": 9.78, "avg_loss": -21.93, "pl_ratio": 0.4458, "touch_count": 11}], "S|SMA|60": [{"period": 2, "win_rate": 47.37, "avg_win": 4.27, "avg_loss": -6.18, "pl_ratio": 0.6903, "touch_count": 19}, {"period": 3, "win_rate": 57.89, "avg_win": 10.14, "avg_loss": -6.49, "pl_ratio": 1.5642, "touch_count": 19}, {"period": 5, "win_rate": 47.37, "avg_win": 15.03, "avg_loss": -7.29, "pl_ratio": 2.0631, "touch_count": 19}, {"period": 10, "win_rate": 47.37, "avg_win": 14.79, "avg_loss": -9.74, "pl_ratio": 1.5186, "touch_count": 19}, {"period": 20, "win_rate": 63.16, "avg_win": 23.79, "avg_loss": -16.06, "pl_ratio": 1.4807, "touch_count": 19}, {"period": 60, "win_rate": 83.33, "avg_win": 30.64, "avg_loss": -14.18, "pl_ratio": 2.1605, "touch_count": 18}, {"period": 126, "win_rate": 50.0, "avg_win": 76.15, "avg_loss": -11.11, "pl_ratio": 6.855, "touch_count": 16}, {"period": 252, "win_rate": 76.92, "avg_win": 103.32, "avg_loss": -16.54, "pl_ratio": 6.2471, "touch_count": 13}], "L|EMA|10": [{"period": 2, "win_rate": 52.08, "avg_win": 3.89, "avg_loss": -2.7, "pl_ratio": 1.4418, "touch_count": 48}, {"period": 3, "win_rate": 64.58, "avg_win": 4.39, "avg_loss": -5.07, "pl_ratio": 0.8657, "touch_count": 48}, {"period": 5, "win_rate": 66.67, "avg_win": 7.83, "avg_loss": -7.9, "pl_ratio": 0.9909, "touch_count": 48}, {"period": 10, "win_rate": 55.32, "avg_win": 13.71, "avg_loss": -8.43, "pl_ratio": 1.6265, "touch_count": 47}, {"period": 20, "win_rate": 63.83, "avg_win": 17.32, "avg_loss": -10.08, "pl_ratio": 1.718, "touch_count": 47}, {"period": 60, "win_rate": 60.0, "avg_win": 22.22, "avg_loss": -14.55, "pl_ratio": 1.527, "touch_count": 40}, {"period": 126, "win_rate": 45.16, "avg_win": 29.87, "avg_loss": -26.22, "pl_ratio": 1.1393, "touch_count": 31}, {"period": 252, "win_rate": 17.39, "avg_win": 7.85, "avg_loss": -16.01, "pl_ratio": 0.4905, "touch_count": 23}], "S|EMA|10": [{"period": 2, "win_rate": 58.62, "avg_win": 3.53, "avg_loss": -3.33, "pl_ratio": 1.0584, "touch_count": 58}, {"period": 3, "win_rate": 62.07, "avg_win": 4.53, "avg_loss": -4.79, "pl_ratio": 0.9451, "touch_count": 58}, {"period": 5, "win_rate": 63.79, "avg_win": 8.19, "avg_loss": -8.3, "pl_ratio": 0.9871, "touch_count": 58}, {"period": 10, "win_rate": 49.12, "avg_win": 16.44, "avg_loss": -10.22, "pl_ratio": 1.609, "touch_count": 57}, {"period": 20, "win_rate": 61.4, "avg_win": 22.46, "avg_loss": -11.13, "pl_ratio": 2.017, "touch_count": 57}, {"period": 60, "win_rate": 60.38, "avg_win": 39.02, "avg_loss": -17.29, "pl_ratio": 2.256, "touch_count": 53}, {"period": 126, "win_rate": 55.1, "avg_win": 55.31, "avg_loss": -21.42, "pl_ratio": 2.5815, "touch_count": 49}, {"period": 252, "win_rate": 52.63, "avg_win": 84.87, "avg_loss": -19.7, "pl_ratio": 4.3078, "touch_count": 38}], "L|EMA|21": [{"period": 2, "win_rate": 51.61, "avg_win": 3.65, "avg_loss": -3.57, "pl_ratio": 1.0199, "touch_count": 31}, {"period": 3, "win_rate": 64.52, "avg_win": 4.19, "avg_loss": -6.35, "pl_ratio": 0.6596, "touch_count": 31}, {"period": 5, "win_rate": 64.52, "avg_win": 9.35, "avg_loss": -7.82, "pl_ratio": 1.1965, "touch_count": 31}, {"period": 10, "win_rate": 51.61, "avg_win": 16.05, "avg_loss": -8.45, "pl_ratio": 1.9002, "touch_count": 31}, {"period": 20, "win_rate": 51.61, "avg_win": 23.05, "avg_loss": -12.36, "pl_ratio": 1.8653, "touch_count": 31}, {"period": 60, "win_rate": 52.0, "avg_win": 19.84, "avg_loss": -19.1, "pl_ratio": 1.0389, "touch_count": 25}, {"period": 126, "win_rate": 31.58, "avg_win": 39.96, "avg_loss": -28.53, "pl_ratio": 1.4003, "touch_count": 19}, {"period": 252, "win_rate": 18.75, "avg_win": 6.87, "avg_loss": -15.47, "pl_ratio": 0.4441, "touch_count": 16}], "S|EMA|21": [{"period": 2, "win_rate": 51.35, "avg_win": 4.98, "avg_loss": -5.1, "pl_ratio": 0.9754, "touch_count": 37}, {"period": 3, "win_rate": 48.65, "avg_win": 5.72, "avg_loss": -6.33, "pl_ratio": 0.9037, "touch_count": 37}, {"period": 5, "win_rate": 56.76, "avg_win": 10.19, "avg_loss": -8.92, "pl_ratio": 1.1428, "touch_count": 37}, {"period": 10, "win_rate": 48.65, "avg_win": 17.1, "avg_loss": -10.62, "pl_ratio": 1.6106, "touch_count": 37}, {"period": 20, "win_rate": 51.35, "avg_win": 27.05, "avg_loss": -9.72, "pl_ratio": 2.7839, "touch_count": 37}, {"period": 60, "win_rate": 52.94, "avg_win": 29.94, "avg_loss": -18.46, "pl_ratio": 1.6218, "touch_count": 34}, {"period": 126, "win_rate": 50.0, "avg_win": 68.72, "avg_loss": -24.9, "pl_ratio": 2.7603, "touch_count": 30}, {"period": 252, "win_rate": 50.0, "avg_win": 94.7, "avg_loss": -17.8, "pl_ratio": 5.3188, "touch_count": 24}], "L|EMA|30": [{"period": 2, "win_rate": 53.33, "avg_win": 4.07, "avg_loss": -3.36, "pl_ratio": 1.21, "touch_count": 30}, {"period": 3, "win_rate": 56.67, "avg_win": 4.22, "avg_loss": -5.27, "pl_ratio": 0.8013, "touch_count": 30}, {"period": 5, "win_rate": 63.33, "avg_win": 8.53, "avg_loss": -6.3, "pl_ratio": 1.3542, "touch_count": 30}, {"period": 10, "win_rate": 53.33, "avg_win": 14.03, "avg_loss": -7.14, "pl_ratio": 1.9649, "touch_count": 30}, {"period": 20, "win_rate": 56.67, "avg_win": 22.35, "avg_loss": -14.03, "pl_ratio": 1.5927, "touch_count": 30}, {"period": 60, "win_rate": 43.48, "avg_win": 24.74, "avg_loss": -20.22, "pl_ratio": 1.2231, "touch_count": 23}, {"period": 126, "win_rate": 18.75, "avg_win": 12.65, "avg_loss": -26.75, "pl_ratio": 0.473, "touch_count": 16}, {"period": 252, "win_rate": 25.0, "avg_win": 5.28, "avg_loss": -14.98, "pl_ratio": 0.3522, "touch_count": 16}], "S|EMA|30": [{"period": 2, "win_rate": 58.06, "avg_win": 4.56, "avg_loss": -5.8, "pl_ratio": 0.786, "touch_count": 31}, {"period": 3, "win_rate": 45.16, "avg_win": 9.67, "avg_loss": -5.77, "pl_ratio": 1.674, "touch_count": 31}, {"period": 5, "win_rate": 58.06, "avg_win": 15.25, "avg_loss": -7.65, "pl_ratio": 1.9942, "touch_count": 31}, {"period": 10, "win_rate": 54.84, "avg_win": 23.95, "avg_loss": -10.81, "pl_ratio": 2.2146, "touch_count": 31}, {"period": 20, "win_rate": 61.29, "avg_win": 30.14, "avg_loss": -10.96, "pl_ratio": 2.7493, "touch_count": 31}, {"period": 60, "win_rate": 48.15, "avg_win": 33.46, "avg_loss": -19.69, "pl_ratio": 1.6993, "touch_count": 27}, {"period": 126, "win_rate": 44.0, "avg_win": 60.56, "avg_loss": -24.81, "pl_ratio": 2.4414, "touch_count": 25}, {"period": 252, "win_rate": 52.17, "avg_win": 74.25, "avg_loss": -16.07, "pl_ratio": 4.6207, "touch_count": 23}], "L|EMA|40": [{"period": 2, "win_rate": 53.85, "avg_win": 4.58, "avg_loss": -3.3, "pl_ratio": 1.3871, "touch_count": 26}, {"period": 3, "win_rate": 73.08, "avg_win": 6.83, "avg_loss": -5.23, "pl_ratio": 1.3075, "touch_count": 26}, {"period": 5, "win_rate": 73.08, "avg_win": 9.16, "avg_loss": -6.44, "pl_ratio": 1.4227, "touch_count": 26}, {"period": 10, "win_rate": 65.38, "avg_win": 17.93, "avg_loss": -7.33, "pl_ratio": 2.4481, "touch_count": 26}, {"period": 20, "win_rate": 61.54, "avg_win": 24.55, "avg_loss": -15.06, "pl_ratio": 1.6304, "touch_count": 26}, {"period": 60, "win_rate": 45.0, "avg_win": 21.38, "avg_loss": -15.97, "pl_ratio": 1.3388, "touch_count": 20}, {"period": 126, "win_rate": 14.29, "avg_win": 14.13, "avg_loss": -20.36, "pl_ratio": 0.6939, "touch_count": 14}, {"period": 252, "win_rate": 14.29, "avg_win": 3.2, "avg_loss": -15.81, "pl_ratio": 0.2025, "touch_count": 14}], "S|EMA|40": [{"period": 2, "win_rate": 54.17, "avg_win": 4.57, "avg_loss": -5.28, "pl_ratio": 0.8664, "touch_count": 24}, {"period": 3, "win_rate": 66.67, "avg_win": 8.2, "avg_loss": -6.7, "pl_ratio": 1.2235, "touch_count": 24}, {"period": 5, "win_rate": 66.67, "avg_win": 11.04, "avg_loss": -8.05, "pl_ratio": 1.3718, "touch_count": 24}, {"period": 10, "win_rate": 58.33, "avg_win": 12.74, "avg_loss": -10.77, "pl_ratio": 1.1826, "touch_count": 24}, {"period": 20, "win_rate": 58.33, "avg_win": 18.39, "avg_loss": -10.08, "pl_ratio": 1.8244, "touch_count": 24}, {"period": 60, "win_rate": 45.45, "avg_win": 25.26, "avg_loss": -15.18, "pl_ratio": 1.6643, "touch_count": 22}, {"period": 126, "win_rate": 47.62, "avg_win": 55.09, "avg_loss": -21.39, "pl_ratio": 2.5757, "touch_count": 21}, {"period": 252, "win_rate": 52.63, "avg_win": 95.26, "avg_loss": -17.26, "pl_ratio": 5.5183, "touch_count": 19}], "L|EMA|50": [{"period": 2, "win_rate": 48.15, "avg_win": 3.42, "avg_loss": -3.73, "pl_ratio": 0.9155, "touch_count": 27}, {"period": 3, "win_rate": 59.26, "avg_win": 4.34, "avg_loss": -5.51, "pl_ratio": 0.7866, "touch_count": 27}, {"period": 5, "win_rate": 55.56, "avg_win": 5.18, "avg_loss": -5.34, "pl_ratio": 0.9688, "touch_count": 27}, {"period": 10, "win_rate": 55.56, "avg_win": 14.93, "avg_loss": -7.01, "pl_ratio": 2.131, "touch_count": 27}, {"period": 20, "win_rate": 55.56, "avg_win": 21.17, "avg_loss": -12.67, "pl_ratio": 1.6704, "touch_count": 27}, {"period": 60, "win_rate": 42.11, "avg_win": 19.25, "avg_loss": -17.18, "pl_ratio": 1.1204, "touch_count": 19}, {"period": 126, "win_rate": 23.08, "avg_win": 12.76, "avg_loss": -19.77, "pl_ratio": 0.6452, "touch_count": 13}, {"period": 252, "win_rate": 23.08, "avg_win": 19.46, "avg_loss": -18.93, "pl_ratio": 1.028, "touch_count": 13}], "S|EMA|50": [{"period": 2, "win_rate": 57.14, "avg_win": 2.78, "avg_loss": -4.14, "pl_ratio": 0.6704, "touch_count": 21}, {"period": 3, "win_rate": 57.14, "avg_win": 4.0, "avg_loss": -4.61, "pl_ratio": 0.8683, "touch_count": 21}, {"period": 5, "win_rate": 52.38, "avg_win": 7.44, "avg_loss": -4.91, "pl_ratio": 1.5143, "touch_count": 21}, {"period": 10, "win_rate": 52.38, "avg_win": 8.66, "avg_loss": -10.06, "pl_ratio": 0.8609, "touch_count": 21}, {"period": 20, "win_rate": 57.14, "avg_win": 14.43, "avg_loss": -7.58, "pl_ratio": 1.9039, "touch_count": 21}, {"period": 60, "win_rate": 58.82, "avg_win": 21.05, "avg_loss": -11.46, "pl_ratio": 1.837, "touch_count": 17}, {"period": 126, "win_rate": 52.94, "avg_win": 59.71, "avg_loss": -14.12, "pl_ratio": 4.2289, "touch_count": 17}, {"period": 252, "win_rate": 53.33, "avg_win": 111.3, "avg_loss": -21.25, "pl_ratio": 5.2372, "touch_count": 15}], "L|EMA|60": [{"period": 2, "win_rate": 50.0, "avg_win": 4.02, "avg_loss": -3.8, "pl_ratio": 1.057, "touch_count": 22}, {"period": 3, "win_rate": 72.73, "avg_win": 3.93, "avg_loss": -7.08, "pl_ratio": 0.5553, "touch_count": 22}, {"period": 5, "win_rate": 63.64, "avg_win": 6.05, "avg_loss": -7.19, "pl_ratio": 0.8416, "touch_count": 22}, {"period": 10, "win_rate": 59.09, "avg_win": 16.0, "avg_loss": -7.17, "pl_ratio": 2.2323, "touch_count": 22}, {"period": 20, "win_rate": 59.09, "avg_win": 23.45, "avg_loss": -10.72, "pl_ratio": 2.1869, "touch_count": 22}, {"period": 60, "win_rate": 40.0, "avg_win": 21.55, "avg_loss": -17.87, "pl_ratio": 1.2064, "touch_count": 15}, {"period": 126, "win_rate": 18.18, "avg_win": 13.4, "avg_loss": -20.53, "pl_ratio": 0.6525, "touch_count": 11}, {"period": 252, "win_rate": 36.36, "avg_win": 18.56, "avg_loss": -18.89, "pl_ratio": 0.9828, "touch_count": 11}], "S|EMA|60": [{"period": 2, "win_rate": 52.94, "avg_win": 2.99, "avg_loss": -4.23, "pl_ratio": 0.7055, "touch_count": 17}, {"period": 3, "win_rate": 58.82, "avg_win": 4.82, "avg_loss": -3.22, "pl_ratio": 1.4969, "touch_count": 17}, {"period": 5, "win_rate": 64.71, "avg_win": 7.5, "avg_loss": -5.66, "pl_ratio": 1.3258, "touch_count": 17}, {"period": 10, "win_rate": 64.71, "avg_win": 8.91, "avg_loss": -7.86, "pl_ratio": 1.1335, "touch_count": 17}, {"period": 20, "win_rate": 64.71, "avg_win": 15.27, "avg_loss": -13.3, "pl_ratio": 1.1483, "touch_count": 17}, {"period": 60, "win_rate": 60.0, "avg_win": 22.59, "avg_loss": -7.82, "pl_ratio": 2.8903, "touch_count": 15}, {"period": 126, "win_rate": 46.67, "avg_win": 75.63, "avg_loss": -14.76, "pl_ratio": 5.125, "touch_count": 15}, {"period": 252, "win_rate": 69.23, "avg_win": 98.86, "avg_loss": -17.33, "pl_ratio": 5.7062, "touch_count": 13}]}}, "box": {"ticker": "APGE", "found": true, "vol_data_available": true, "periods_all": {"L": [{"filter": "L", "period": 2, "win_rate": null, "avg_win": null, "avg_loss": null, "pl_ratio": null, "cnt": 0}, {"filter": "L", "period": 3, "win_rate": null, "avg_win": null, "avg_loss": null, "pl_ratio": null, "cnt": 0}, {"filter": "L", "period": 5, "win_rate": null, "avg_win": null, "avg_loss": null, "pl_ratio": null, "cnt": 0}, {"filter": "L", "period": 10, "win_rate": null, "avg_win": null, "avg_loss": null, "pl_ratio": null, "cnt": 0}, {"filter": "L", "period": 20, "win_rate": null, "avg_win": null, "avg_loss": null, "pl_ratio": null, "cnt": 0}, {"filter": "L", "period": 63, "win_rate": null, "avg_win": null, "avg_loss": null, "pl_ratio": null, "cnt": 0}, {"filter": "L", "period": 126, "win_rate": null, "avg_win": null, "avg_loss": null, "pl_ratio": null, "cnt": 0}, {"filter": "L", "period": 252, "win_rate": null, "avg_win": null, "avg_loss": null, "pl_ratio": null, "cnt": 0}], "S": [{"filter": "S", "period": 2, "win_rate": 25.0, "avg_win": 0.03, "avg_loss": -1.19, "pl_ratio": 0.0268, "cnt": 4}, {"filter": "S", "period": 3, "win_rate": 50.0, "avg_win": 4.45, "avg_loss": -0.51, "pl_ratio": 8.6846, "cnt": 4}, {"filter": "S", "period": 5, "win_rate": 25.0, "avg_win": 1.53, "avg_loss": -1.59, "pl_ratio": 0.962, "cnt": 4}, {"filter": "S", "period": 10, "win_rate": 50.0, "avg_win": 24.08, "avg_loss": -17.65, "pl_ratio": 1.3645, "cnt": 4}, {"filter": "S", "period": 20, "win_rate": 50.0, "avg_win": 31.0, "avg_loss": -13.34, "pl_ratio": 2.3245, "cnt": 4}, {"filter": "S", "period": 63, "win_rate": 75.0, "avg_win": 37.24, "avg_loss": -31.86, "pl_ratio": 1.1689, "cnt": 4}, {"filter": "S", "period": 126, "win_rate": 75.0, "avg_win": 69.06, "avg_loss": -36.03, "pl_ratio": 1.9169, "cnt": 4}, {"filter": "S", "period": 252, "win_rate": 0.0, "avg_win": 0.0, "avg_loss": -6.14, "pl_ratio": 0.0, "cnt": 1}]}, "periods_vol2x": {"L": [{"filter": "L", "period": 2, "win_rate": null, "avg_win": null, "avg_loss": null, "pl_ratio": null, "cnt": 0}, {"filter": "L", "period": 3, "win_rate": null, "avg_win": null, "avg_loss": null, "pl_ratio": null, "cnt": 0}, {"filter": "L", "period": 5, "win_rate": null, "avg_win": null, "avg_loss": null, "pl_ratio": null, "cnt": 0}, {"filter": "L", "period": 10, "win_rate": null, "avg_win": null, "avg_loss": null, "pl_ratio": null, "cnt": 0}, {"filter": "L", "period": 20, "win_rate": null, "avg_win": null, "avg_loss": null, "pl_ratio": null, "cnt": 0}, {"filter": "L", "period": 63, "win_rate": null, "avg_win": null, "avg_loss": null, "pl_ratio": null, "cnt": 0}, {"filter": "L", "period": 126, "win_rate": null, "avg_win": null, "avg_loss": null, "pl_ratio": null, "cnt": 0}, {"filter": "L", "period": 252, "win_rate": null, "avg_win": null, "avg_loss": null, "pl_ratio": null, "cnt": 0}], "S": [{"filter": "S", "period": 2, "win_rate": 100.0, "avg_win": 0.03, "avg_loss": null, "pl_ratio": null, "cnt": 1}, {"filter": "S", "period": 3, "win_rate": 100.0, "avg_win": 4.05, "avg_loss": null, "pl_ratio": null, "cnt": 1}, {"filter": "S", "period": 5, "win_rate": 100.0, "avg_win": 1.53, "avg_loss": null, "pl_ratio": null, "cnt": 1}, {"filter": "S", "period": 10, "win_rate": 100.0, "avg_win": 12.66, "avg_loss": null, "pl_ratio": null, "cnt": 1}, {"filter": "S", "period": 20, "win_rate": 100.0, "avg_win": 20.83, "avg_loss": null, "pl_ratio": null, "cnt": 1}, {"filter": "S", "period": 63, "win_rate": 100.0, "avg_win": 10.1, "avg_loss": null, "pl_ratio": null, "cnt": 1}, {"filter": "S", "period": 126, "win_rate": 100.0, "avg_win": 33.3, "avg_loss": null, "pl_ratio": null, "cnt": 1}, {"filter": "S", "period": 252, "win_rate": null, "avg_win": null, "avg_loss": null, "pl_ratio": null, "cnt": 0}]}, "breakout_vol_mult": 2}, "nhigh": {"ticker": "APGE", "found": true, "market": "US", "last_close": 134.2, "last_date": "2026-07-21", "holds": [2, 3, 5, 10, 20, 60, 126, 252], "entries": {"ATH": {"distance_pct": 0.07, "label": "대기", "breakout_pct": 0.02, "near_pct": null, "days_since_breakout": 9, "holds": [{"hold": 2, "n": 27, "win_rate": 66.67, "avg_ret": 2.72, "median_ret": 0.47, "avg_win": 5.55, "avg_loss": -2.95, "pl_ratio": 1.8794}, {"hold": 3, "n": 27, "win_rate": 66.67, "avg_ret": 4.56, "median_ret": 0.87, "avg_win": 7.88, "avg_loss": -2.1, "pl_ratio": 3.7566}, {"hold": 5, "n": 27, "win_rate": 70.37, "avg_ret": 5.51, "median_ret": 2.03, "avg_win": 8.95, "avg_loss": -2.64, "pl_ratio": 3.3845}, {"hold": 10, "n": 26, "win_rate": 76.92, "avg_ret": 5.5, "median_ret": 2.55, "avg_win": 8.56, "avg_loss": -4.69, "pl_ratio": 1.8245}, {"hold": 20, "n": 25, "win_rate": 56.0, "avg_ret": 2.92, "median_ret": 1.65, "avg_win": 14.83, "avg_loss": -12.25, "pl_ratio": 1.2106}, {"hold": 60, "n": 24, "win_rate": 45.83, "avg_ret": 12.2, "median_ret": -4.32, "avg_win": 52.3, "avg_loss": -21.73, "pl_ratio": 2.4068}, {"hold": 126, "n": 21, "win_rate": 90.48, "avg_ret": 45.19, "median_ret": 51.09, "avg_win": 52.93, "avg_loss": -28.33, "pl_ratio": 1.8685}, {"hold": 252, "n": 14, "win_rate": 78.57, "avg_ret": 55.21, "median_ret": 89.04, "avg_win": 79.44, "avg_loss": -33.65, "pl_ratio": 2.3607}]}, "20": {"distance_pct": 0.07, "label": "대기", "breakout_pct": 0.02, "near_pct": null, "days_since_breakout": 9, "holds": [{"hold": 2, "n": 59, "win_rate": 49.15, "avg_ret": 0.52, "median_ret": -0.38, "avg_win": 5.29, "avg_loss": -4.08, "pl_ratio": 1.2955}, {"hold": 3, "n": 59, "win_rate": 57.63, "avg_ret": 2.22, "median_ret": 0.36, "avg_win": 7.05, "avg_loss": -4.35, "pl_ratio": 1.6181}, {"hold": 5, "n": 59, "win_rate": 52.54, "avg_ret": 2.7, "median_ret": 0.38, "avg_win": 9.2, "avg_loss": -4.49, "pl_ratio": 2.0494}, {"hold": 10, "n": 58, "win_rate": 58.62, "avg_ret": 2.75, "median_ret": 1.03, "avg_win": 10.51, "avg_loss": -8.24, "pl_ratio": 1.2753}, {"hold": 20, "n": 57, "win_rate": 52.63, "avg_ret": 3.98, "median_ret": 1.65, "avg_win": 19.21, "avg_loss": -12.94, "pl_ratio": 1.485}, {"hold": 60, "n": 55, "win_rate": 54.55, "avg_ret": 17.63, "median_ret": 3.21, "avg_win": 46.99, "avg_loss": -17.6, "pl_ratio": 2.6694}, {"hold": 126, "n": 49, "win_rate": 69.39, "avg_ret": 35.92, "median_ret": 42.2, "avg_win": 61.83, "avg_loss": -22.82, "pl_ratio": 2.7093}, {"hold": 252, "n": 33, "win_rate": 66.67, "avg_ret": 47.69, "median_ret": 65.48, "avg_win": 85.03, "avg_loss": -26.98, "pl_ratio": 3.1515}]}, "55": {"distance_pct": 0.07, "label": "대기", "breakout_pct": 0.02, "near_pct": null, "days_since_breakout": 9, "holds": [{"hold": 2, "n": 37, "win_rate": 54.05, "avg_ret": 1.29, "median_ret": 0.11, "avg_win": 6.22, "avg_loss": -4.51, "pl_ratio": 1.3789}, {"hold": 3, "n": 37, "win_rate": 59.46, "avg_ret": 3.0, "median_ret": 0.87, "avg_win": 8.12, "avg_loss": -4.52, "pl_ratio": 1.7965}, {"hold": 5, "n": 37, "win_rate": 64.86, "avg_ret": 3.91, "median_ret": 1.53, "avg_win": 9.11, "avg_loss": -5.7, "pl_ratio": 1.5988}, {"hold": 10, "n": 36, "win_rate": 69.44, "avg_ret": 4.04, "median_ret": 1.3, "avg_win": 9.14, "avg_loss": -7.57, "pl_ratio": 1.2074}, {"hold": 20, "n": 35, "win_rate": 60.0, "avg_ret": 4.29, "median_ret": 5.19, "avg_win": 16.18, "avg_loss": -13.53, "pl_ratio": 1.1952}, {"hold": 60, "n": 34, "win_rate": 50.0, "avg_ret": 20.67, "median_ret": 0.96, "avg_win": 57.22, "avg_loss": -15.87, "pl_ratio": 3.6055}, {"hold": 126, "n": 31, "win_rate": 74.19, "avg_ret": 30.75, "median_ret": 48.71, "avg_win": 52.15, "avg_loss": -30.75, "pl_ratio": 1.6958}, {"hold": 252, "n": 18, "win_rate": 55.56, "avg_ret": 27.37, "median_ret": 7.96, "avg_win": 74.72, "avg_loss": -31.81, "pl_ratio": 2.3491}]}}, "signal": null}}