{"ma": {"ticker": "CLYM", "found": true, "last_close": 12.58, "last_date": "2026-07-22", "benchmark": "^GSPC", "market_s": true, "ticker_long": true, "ticker_short": false, "mas": [{"ma_type": "SMA", "ma_period": 10, "ma_value": 12.765, "distance_pct": -1.45}, {"ma_type": "SMA", "ma_period": 20, "ma_value": 13.1815, "distance_pct": -4.56}, {"ma_type": "SMA", "ma_period": 30, "ma_value": 13.2, "distance_pct": -4.7}, {"ma_type": "SMA", "ma_period": 40, "ma_value": 13.126, "distance_pct": -4.16}, {"ma_type": "SMA", "ma_period": 50, "ma_value": 12.8038, "distance_pct": -1.75}, {"ma_type": "SMA", "ma_period": 60, "ma_value": 12.517, "distance_pct": 0.5}, {"ma_type": "EMA", "ma_period": 10, "ma_value": 12.8323, "distance_pct": -1.97}, {"ma_type": "EMA", "ma_period": 21, "ma_value": 12.9629, "distance_pct": -2.95}, {"ma_type": "EMA", "ma_period": 30, "ma_value": 12.9318, "distance_pct": -2.72}, {"ma_type": "EMA", "ma_period": 40, "ma_value": 12.825, "distance_pct": -1.91}, {"ma_type": "EMA", "ma_period": 50, "ma_value": 12.6837, "distance_pct": -0.82}, {"ma_type": "EMA", "ma_period": 60, "ma_value": 12.5258, "distance_pct": 0.43}], "stats": {"L|SMA|10": [{"period": 2, "win_rate": 45.0, "avg_win": 3.71, "avg_loss": -3.57, "pl_ratio": 1.0398, "touch_count": 80}, {"period": 3, "win_rate": 45.57, "avg_win": 4.08, "avg_loss": -3.74, "pl_ratio": 1.0901, "touch_count": 79}, {"period": 5, "win_rate": 37.97, "avg_win": 7.14, "avg_loss": -4.41, "pl_ratio": 1.62, "touch_count": 79}, {"period": 10, "win_rate": 46.84, "avg_win": 8.25, "avg_loss": -7.99, "pl_ratio": 1.0321, "touch_count": 79}, {"period": 20, "win_rate": 42.86, "avg_win": 16.81, "avg_loss": -8.19, "pl_ratio": 2.0527, "touch_count": 77}, {"period": 60, "win_rate": 55.41, "avg_win": 47.91, "avg_loss": -10.95, "pl_ratio": 4.3737, "touch_count": 74}, {"period": 126, "win_rate": 57.81, "avg_win": 100.08, "avg_loss": -20.22, "pl_ratio": 4.9504, "touch_count": 64}, {"period": 252, "win_rate": 61.11, "avg_win": 250.28, "avg_loss": -47.45, "pl_ratio": 5.2744, "touch_count": 54}], "S|SMA|10": [{"period": 2, "win_rate": 41.74, "avg_win": 4.31, "avg_loss": -3.92, "pl_ratio": 1.0993, "touch_count": 115}, {"period": 3, "win_rate": 41.23, "avg_win": 4.92, "avg_loss": -4.11, "pl_ratio": 1.1961, "touch_count": 114}, {"period": 5, "win_rate": 38.6, "avg_win": 6.6, "avg_loss": -4.29, "pl_ratio": 1.5384, "touch_count": 114}, {"period": 10, "win_rate": 42.11, "avg_win": 7.71, "avg_loss": -7.79, "pl_ratio": 0.9895, "touch_count": 114}, {"period": 20, "win_rate": 37.5, "avg_win": 16.05, "avg_loss": -9.64, "pl_ratio": 1.6656, "touch_count": 112}, {"period": 60, "win_rate": 43.64, "avg_win": 33.63, "avg_loss": -16.89, "pl_ratio": 1.9907, "touch_count": 110}, {"period": 126, "win_rate": 45.54, "avg_win": 67.27, "avg_loss": -25.94, "pl_ratio": 2.593, "touch_count": 101}, {"period": 252, "win_rate": 45.74, "avg_win": 177.44, "avg_loss": -38.3, "pl_ratio": 4.633, "touch_count": 94}], "L|SMA|20": [{"period": 2, "win_rate": 50.68, "avg_win": 4.04, "avg_loss": -3.72, "pl_ratio": 1.0851, "touch_count": 73}, {"period": 3, "win_rate": 51.39, "avg_win": 4.79, "avg_loss": -4.32, "pl_ratio": 1.1098, "touch_count": 72}, {"period": 5, "win_rate": 50.0, "avg_win": 7.62, "avg_loss": -5.06, "pl_ratio": 1.5044, "touch_count": 72}, {"period": 10, "win_rate": 43.06, "avg_win": 16.53, "avg_loss": -6.84, "pl_ratio": 2.4175, "touch_count": 72}, {"period": 20, "win_rate": 47.89, "avg_win": 25.69, "avg_loss": -8.95, "pl_ratio": 2.8687, "touch_count": 71}, {"period": 60, "win_rate": 58.21, "avg_win": 46.56, "avg_loss": -10.06, "pl_ratio": 4.6289, "touch_count": 67}, {"period": 126, "win_rate": 68.85, "avg_win": 109.68, "avg_loss": -19.39, "pl_ratio": 5.6559, "touch_count": 61}, {"period": 252, "win_rate": 68.0, "avg_win": 225.29, "avg_loss": -52.59, "pl_ratio": 4.2841, "touch_count": 50}], "S|SMA|20": [{"period": 2, "win_rate": 49.04, "avg_win": 4.6, "avg_loss": -3.81, "pl_ratio": 1.2061, "touch_count": 104}, {"period": 3, "win_rate": 48.54, "avg_win": 4.92, "avg_loss": -4.28, "pl_ratio": 1.1516, "touch_count": 103}, {"period": 5, "win_rate": 43.69, "avg_win": 6.96, "avg_loss": -4.68, "pl_ratio": 1.4872, "touch_count": 103}, {"period": 10, "win_rate": 44.66, "avg_win": 11.78, "avg_loss": -6.63, "pl_ratio": 1.7771, "touch_count": 103}, {"period": 20, "win_rate": 43.14, "avg_win": 20.37, "avg_loss": -9.16, "pl_ratio": 2.2236, "touch_count": 102}, {"period": 60, "win_rate": 45.0, "avg_win": 38.1, "avg_loss": -16.3, "pl_ratio": 2.3374, "touch_count": 100}, {"period": 126, "win_rate": 57.45, "avg_win": 70.59, "avg_loss": -24.48, "pl_ratio": 2.8831, "touch_count": 94}, {"period": 252, "win_rate": 55.29, "avg_win": 158.3, "avg_loss": -37.91, "pl_ratio": 4.176, "touch_count": 85}], "L|SMA|30": [{"period": 2, "win_rate": 48.98, "avg_win": 3.27, "avg_loss": -3.65, "pl_ratio": 0.8957, "touch_count": 49}, {"period": 3, "win_rate": 47.92, "avg_win": 3.16, "avg_loss": -3.55, "pl_ratio": 0.891, "touch_count": 48}, {"period": 5, "win_rate": 47.92, "avg_win": 5.28, "avg_loss": -4.26, "pl_ratio": 1.2388, "touch_count": 48}, {"period": 10, "win_rate": 47.92, "avg_win": 15.39, "avg_loss": -5.66, "pl_ratio": 2.7188, "touch_count": 48}, {"period": 20, "win_rate": 53.19, "avg_win": 21.6, "avg_loss": -7.22, "pl_ratio": 2.9925, "touch_count": 47}, {"period": 60, "win_rate": 61.36, "avg_win": 39.41, "avg_loss": -9.95, "pl_ratio": 3.9626, "touch_count": 44}, {"period": 126, "win_rate": 66.67, "avg_win": 113.13, "avg_loss": -21.25, "pl_ratio": 5.3226, "touch_count": 36}, {"period": 252, "win_rate": 64.52, "avg_win": 234.23, "avg_loss": -54.25, "pl_ratio": 4.3175, "touch_count": 31}], "S|SMA|30": [{"period": 2, "win_rate": 44.3, "avg_win": 4.12, "avg_loss": -4.07, "pl_ratio": 1.0129, "touch_count": 79}, {"period": 3, "win_rate": 44.87, "avg_win": 3.98, "avg_loss": -4.06, "pl_ratio": 0.9823, "touch_count": 78}, {"period": 5, "win_rate": 41.03, "avg_win": 4.92, "avg_loss": -4.75, "pl_ratio": 1.0343, "touch_count": 78}, {"period": 10, "win_rate": 42.31, "avg_win": 11.03, "avg_loss": -7.88, "pl_ratio": 1.4005, "touch_count": 78}, {"period": 20, "win_rate": 42.86, "avg_win": 14.59, "avg_loss": -9.09, "pl_ratio": 1.6049, "touch_count": 77}, {"period": 60, "win_rate": 44.0, "avg_win": 30.0, "avg_loss": -15.6, "pl_ratio": 1.9228, "touch_count": 75}, {"period": 126, "win_rate": 52.94, "avg_win": 63.53, "avg_loss": -24.62, "pl_ratio": 2.5805, "touch_count": 68}, {"period": 252, "win_rate": 55.38, "avg_win": 130.95, "avg_loss": -39.22, "pl_ratio": 3.3387, "touch_count": 65}], "L|SMA|40": [{"period": 2, "win_rate": 50.0, "avg_win": 4.57, "avg_loss": -3.89, "pl_ratio": 1.1722, "touch_count": 42}, {"period": 3, "win_rate": 51.22, "avg_win": 4.61, "avg_loss": -4.44, "pl_ratio": 1.04, "touch_count": 41}, {"period": 5, "win_rate": 51.22, "avg_win": 8.53, "avg_loss": -4.56, "pl_ratio": 1.871, "touch_count": 41}, {"period": 10, "win_rate": 48.78, "avg_win": 11.05, "avg_loss": -5.48, "pl_ratio": 2.0158, "touch_count": 41}, {"period": 20, "win_rate": 53.66, "avg_win": 12.44, "avg_loss": -7.57, "pl_ratio": 1.6444, "touch_count": 41}, {"period": 60, "win_rate": 61.54, "avg_win": 45.18, "avg_loss": -9.36, "pl_ratio": 4.8285, "touch_count": 39}, {"period": 126, "win_rate": 70.59, "avg_win": 103.94, "avg_loss": -18.02, "pl_ratio": 5.7681, "touch_count": 34}, {"period": 252, "win_rate": 64.29, "avg_win": 238.75, "avg_loss": -50.37, "pl_ratio": 4.7398, "touch_count": 28}], "S|SMA|40": [{"period": 2, "win_rate": 45.45, "avg_win": 4.12, "avg_loss": -4.72, "pl_ratio": 0.8728, "touch_count": 88}, {"period": 3, "win_rate": 45.98, "avg_win": 4.18, "avg_loss": -5.48, "pl_ratio": 0.7614, "touch_count": 87}, {"period": 5, "win_rate": 41.38, "avg_win": 5.73, "avg_loss": -4.98, "pl_ratio": 1.1511, "touch_count": 87}, {"period": 10, "win_rate": 36.78, "avg_win": 7.12, "avg_loss": -7.35, "pl_ratio": 0.9685, "touch_count": 87}, {"period": 20, "win_rate": 42.53, "avg_win": 8.34, "avg_loss": -9.49, "pl_ratio": 0.8784, "touch_count": 87}, {"period": 60, "win_rate": 38.82, "avg_win": 33.79, "avg_loss": -17.14, "pl_ratio": 1.9718, "touch_count": 85}, {"period": 126, "win_rate": 46.91, "avg_win": 62.38, "avg_loss": -22.78, "pl_ratio": 2.7384, "touch_count": 81}, {"period": 252, "win_rate": 49.35, "avg_win": 138.67, "avg_loss": -36.26, "pl_ratio": 3.8245, "touch_count": 77}], "L|SMA|50": [{"period": 2, "win_rate": 47.73, "avg_win": 4.05, "avg_loss": -3.91, "pl_ratio": 1.0366, "touch_count": 44}, {"period": 3, "win_rate": 48.84, "avg_win": 4.26, "avg_loss": -4.58, "pl_ratio": 0.93, "touch_count": 43}, {"period": 5, "win_rate": 48.84, "avg_win": 8.83, "avg_loss": -4.78, "pl_ratio": 1.8489, "touch_count": 43}, {"period": 10, "win_rate": 52.38, "avg_win": 16.4, "avg_loss": -6.19, "pl_ratio": 2.6496, "touch_count": 42}, {"period": 20, "win_rate": 50.0, "avg_win": 20.84, "avg_loss": -8.61, "pl_ratio": 2.4215, "touch_count": 42}, {"period": 60, "win_rate": 57.5, "avg_win": 69.33, "avg_loss": -7.99, "pl_ratio": 8.6754, "touch_count": 40}, {"period": 126, "win_rate": 63.16, "avg_win": 119.32, "avg_loss": -17.56, "pl_ratio": 6.7948, "touch_count": 38}, {"period": 252, "win_rate": 54.55, "avg_win": 225.18, "avg_loss": -49.26, "pl_ratio": 4.5715, "touch_count": 33}], "S|SMA|50": [{"period": 2, "win_rate": 45.45, "avg_win": 4.38, "avg_loss": -4.51, "pl_ratio": 0.9697, "touch_count": 88}, {"period": 3, "win_rate": 45.98, "avg_win": 4.49, "avg_loss": -5.1, "pl_ratio": 0.8803, "touch_count": 87}, {"period": 5, "win_rate": 41.38, "avg_win": 5.89, "avg_loss": -4.95, "pl_ratio": 1.1886, "touch_count": 87}, {"period": 10, "win_rate": 44.19, "avg_win": 10.64, "avg_loss": -7.31, "pl_ratio": 1.4545, "touch_count": 86}, {"period": 20, "win_rate": 44.19, "avg_win": 14.35, "avg_loss": -9.71, "pl_ratio": 1.4779, "touch_count": 86}, {"period": 60, "win_rate": 35.29, "avg_win": 46.17, "avg_loss": -15.0, "pl_ratio": 3.0774, "touch_count": 85}, {"period": 126, "win_rate": 46.43, "avg_win": 68.21, "avg_loss": -21.06, "pl_ratio": 3.2383, "touch_count": 84}, {"period": 252, "win_rate": 47.56, "avg_win": 130.24, "avg_loss": -36.19, "pl_ratio": 3.599, "touch_count": 82}], "L|SMA|60": [{"period": 2, "win_rate": 48.57, "avg_win": 3.28, "avg_loss": -3.31, "pl_ratio": 0.9919, "touch_count": 35}, {"period": 3, "win_rate": 54.29, "avg_win": 3.45, "avg_loss": -3.54, "pl_ratio": 0.9729, "touch_count": 35}, {"period": 5, "win_rate": 42.86, "avg_win": 6.92, "avg_loss": -5.42, "pl_ratio": 1.2777, "touch_count": 35}, {"period": 10, "win_rate": 48.48, "avg_win": 8.9, "avg_loss": -6.98, "pl_ratio": 1.2749, "touch_count": 33}, {"period": 20, "win_rate": 42.42, "avg_win": 13.17, "avg_loss": -9.93, "pl_ratio": 1.3265, "touch_count": 33}, {"period": 60, "win_rate": 58.06, "avg_win": 67.42, "avg_loss": -7.5, "pl_ratio": 8.9885, "touch_count": 31}, {"period": 126, "win_rate": 71.43, "avg_win": 132.51, "avg_loss": -19.2, "pl_ratio": 6.9003, "touch_count": 28}, {"period": 252, "win_rate": 62.5, "avg_win": 236.13, "avg_loss": -44.11, "pl_ratio": 5.353, "touch_count": 24}], "S|SMA|60": [{"period": 2, "win_rate": 39.51, "avg_win": 3.96, "avg_loss": -4.27, "pl_ratio": 0.9275, "touch_count": 81}, {"period": 3, "win_rate": 39.51, "avg_win": 3.85, "avg_loss": -4.16, "pl_ratio": 0.9261, "touch_count": 81}, {"period": 5, "win_rate": 37.04, "avg_win": 4.97, "avg_loss": -4.57, "pl_ratio": 1.0868, "touch_count": 81}, {"period": 10, "win_rate": 43.04, "avg_win": 9.0, "avg_loss": -6.48, "pl_ratio": 1.3878, "touch_count": 79}, {"period": 20, "win_rate": 44.3, "avg_win": 11.72, "avg_loss": -7.87, "pl_ratio": 1.4902, "touch_count": 79}, {"period": 60, "win_rate": 35.9, "avg_win": 40.91, "avg_loss": -12.89, "pl_ratio": 3.1726, "touch_count": 78}, {"period": 126, "win_rate": 45.45, "avg_win": 66.94, "avg_loss": -20.27, "pl_ratio": 3.3029, "touch_count": 77}, {"period": 252, "win_rate": 48.68, "avg_win": 127.49, "avg_loss": -30.14, "pl_ratio": 4.2296, "touch_count": 76}], "L|EMA|10": [{"period": 2, "win_rate": 45.45, "avg_win": 4.03, "avg_loss": -3.45, "pl_ratio": 1.1675, "touch_count": 99}, {"period": 3, "win_rate": 50.0, "avg_win": 5.2, "avg_loss": -4.36, "pl_ratio": 1.1924, "touch_count": 98}, {"period": 5, "win_rate": 50.0, "avg_win": 7.55, "avg_loss": -5.27, "pl_ratio": 1.4326, "touch_count": 98}, {"period": 10, "win_rate": 50.0, "avg_win": 10.18, "avg_loss": -8.37, "pl_ratio": 1.2162, "touch_count": 98}, {"period": 20, "win_rate": 51.58, "avg_win": 19.32, "avg_loss": -10.16, "pl_ratio": 1.9014, "touch_count": 95}, {"period": 60, "win_rate": 50.55, "avg_win": 40.65, "avg_loss": -10.41, "pl_ratio": 3.9059, "touch_count": 91}, {"period": 126, "win_rate": 59.26, "avg_win": 95.84, "avg_loss": -21.22, "pl_ratio": 4.5157, "touch_count": 81}, {"period": 252, "win_rate": 53.23, "avg_win": 244.4, "avg_loss": -49.04, "pl_ratio": 4.9832, "touch_count": 62}], "S|EMA|10": [{"period": 2, "win_rate": 44.14, "avg_win": 4.4, "avg_loss": -4.21, "pl_ratio": 1.0447, "touch_count": 145}, {"period": 3, "win_rate": 45.14, "avg_win": 5.49, "avg_loss": -4.88, "pl_ratio": 1.1246, "touch_count": 144}, {"period": 5, "win_rate": 47.22, "avg_win": 6.98, "avg_loss": -5.28, "pl_ratio": 1.3209, "touch_count": 144}, {"period": 10, "win_rate": 43.06, "avg_win": 8.91, "avg_loss": -7.46, "pl_ratio": 1.1946, "touch_count": 144}, {"period": 20, "win_rate": 42.55, "avg_win": 16.66, "avg_loss": -11.02, "pl_ratio": 1.5114, "touch_count": 141}, {"period": 60, "win_rate": 42.34, "avg_win": 30.53, "avg_loss": -17.49, "pl_ratio": 1.7456, "touch_count": 137}, {"period": 126, "win_rate": 48.44, "avg_win": 67.25, "avg_loss": -28.49, "pl_ratio": 2.3608, "touch_count": 128}, {"period": 252, "win_rate": 43.75, "avg_win": 153.75, "avg_loss": -41.5, "pl_ratio": 3.7047, "touch_count": 112}], "L|EMA|21": [{"period": 2, "win_rate": 41.79, "avg_win": 3.55, "avg_loss": -3.16, "pl_ratio": 1.1257, "touch_count": 67}, {"period": 3, "win_rate": 43.94, "avg_win": 4.34, "avg_loss": -3.05, "pl_ratio": 1.4203, "touch_count": 66}, {"period": 5, "win_rate": 50.0, "avg_win": 5.23, "avg_loss": -4.49, "pl_ratio": 1.1653, "touch_count": 66}, {"period": 10, "win_rate": 45.45, "avg_win": 11.17, "avg_loss": -6.24, "pl_ratio": 1.7897, "touch_count": 66}, {"period": 20, "win_rate": 49.23, "avg_win": 20.9, "avg_loss": -8.88, "pl_ratio": 2.3525, "touch_count": 65}, {"period": 60, "win_rate": 58.06, "avg_win": 46.54, "avg_loss": -8.99, "pl_ratio": 5.1772, "touch_count": 62}, {"period": 126, "win_rate": 70.37, "avg_win": 113.88, "avg_loss": -18.66, "pl_ratio": 6.104, "touch_count": 54}, {"period": 252, "win_rate": 70.45, "avg_win": 240.81, "avg_loss": -48.51, "pl_ratio": 4.9645, "touch_count": 44}], "S|EMA|21": [{"period": 2, "win_rate": 40.62, "avg_win": 4.39, "avg_loss": -4.01, "pl_ratio": 1.0951, "touch_count": 96}, {"period": 3, "win_rate": 42.11, "avg_win": 4.89, "avg_loss": -4.14, "pl_ratio": 1.1802, "touch_count": 95}, {"period": 5, "win_rate": 43.16, "avg_win": 5.46, "avg_loss": -5.04, "pl_ratio": 1.0826, "touch_count": 95}, {"period": 10, "win_rate": 41.05, "avg_win": 9.47, "avg_loss": -7.43, "pl_ratio": 1.2747, "touch_count": 95}, {"period": 20, "win_rate": 41.49, "avg_win": 17.85, "avg_loss": -9.49, "pl_ratio": 1.8816, "touch_count": 94}, {"period": 60, "win_rate": 39.56, "avg_win": 36.49, "avg_loss": -14.0, "pl_ratio": 2.6074, "touch_count": 91}, {"period": 126, "win_rate": 52.38, "avg_win": 67.59, "avg_loss": -23.28, "pl_ratio": 2.9039, "touch_count": 84}, {"period": 252, "win_rate": 48.68, "avg_win": 152.02, "avg_loss": -34.01, "pl_ratio": 4.4706, "touch_count": 76}], "L|EMA|30": [{"period": 2, "win_rate": 42.86, "avg_win": 4.33, "avg_loss": -3.2, "pl_ratio": 1.3508, "touch_count": 63}, {"period": 3, "win_rate": 43.55, "avg_win": 4.4, "avg_loss": -3.15, "pl_ratio": 1.3952, "touch_count": 62}, {"period": 5, "win_rate": 40.32, "avg_win": 6.48, "avg_loss": -5.26, "pl_ratio": 1.2303, "touch_count": 62}, {"period": 10, "win_rate": 45.16, "avg_win": 14.04, "avg_loss": -6.8, "pl_ratio": 2.065, "touch_count": 62}, {"period": 20, "win_rate": 50.82, "avg_win": 19.99, "avg_loss": -8.72, "pl_ratio": 2.2931, "touch_count": 61}, {"period": 60, "win_rate": 56.67, "avg_win": 50.81, "avg_loss": -9.54, "pl_ratio": 5.3268, "touch_count": 60}, {"period": 126, "win_rate": 69.81, "avg_win": 117.91, "avg_loss": -21.97, "pl_ratio": 5.366, "touch_count": 53}, {"period": 252, "win_rate": 65.22, "avg_win": 241.46, "avg_loss": -52.96, "pl_ratio": 4.5595, "touch_count": 46}], "S|EMA|30": [{"period": 2, "win_rate": 43.96, "avg_win": 5.04, "avg_loss": -4.2, "pl_ratio": 1.1982, "touch_count": 91}, {"period": 3, "win_rate": 44.44, "avg_win": 5.04, "avg_loss": -4.14, "pl_ratio": 1.2159, "touch_count": 90}, {"period": 5, "win_rate": 38.89, "avg_win": 5.68, "avg_loss": -5.42, "pl_ratio": 1.049, "touch_count": 90}, {"period": 10, "win_rate": 43.33, "avg_win": 10.04, "avg_loss": -7.59, "pl_ratio": 1.3237, "touch_count": 90}, {"period": 20, "win_rate": 43.82, "avg_win": 16.27, "avg_loss": -9.09, "pl_ratio": 1.7893, "touch_count": 89}, {"period": 60, "win_rate": 37.5, "avg_win": 39.1, "avg_loss": -14.72, "pl_ratio": 2.6557, "touch_count": 88}, {"period": 126, "win_rate": 53.66, "avg_win": 69.74, "avg_loss": -24.43, "pl_ratio": 2.8543, "touch_count": 82}, {"period": 252, "win_rate": 48.72, "avg_win": 148.67, "avg_loss": -34.15, "pl_ratio": 4.3536, "touch_count": 78}], "L|EMA|40": [{"period": 2, "win_rate": 36.0, "avg_win": 4.59, "avg_loss": -3.99, "pl_ratio": 1.1512, "touch_count": 50}, {"period": 3, "win_rate": 38.78, "avg_win": 4.55, "avg_loss": -3.89, "pl_ratio": 1.1698, "touch_count": 49}, {"period": 5, "win_rate": 40.82, "avg_win": 7.92, "avg_loss": -5.26, "pl_ratio": 1.5063, "touch_count": 49}, {"period": 10, "win_rate": 47.92, "avg_win": 15.59, "avg_loss": -6.61, "pl_ratio": 2.3583, "touch_count": 48}, {"period": 20, "win_rate": 54.17, "avg_win": 20.02, "avg_loss": -9.5, "pl_ratio": 2.1069, "touch_count": 48}, {"period": 60, "win_rate": 54.35, "avg_win": 55.3, "avg_loss": -9.2, "pl_ratio": 6.0127, "touch_count": 46}, {"period": 126, "win_rate": 71.43, "avg_win": 120.0, "avg_loss": -20.25, "pl_ratio": 5.9251, "touch_count": 42}, {"period": 252, "win_rate": 65.71, "avg_win": 243.76, "avg_loss": -47.44, "pl_ratio": 5.138, "touch_count": 35}], "S|EMA|40": [{"period": 2, "win_rate": 41.3, "avg_win": 4.82, "avg_loss": -4.99, "pl_ratio": 0.9658, "touch_count": 92}, {"period": 3, "win_rate": 42.86, "avg_win": 4.97, "avg_loss": -5.12, "pl_ratio": 0.9705, "touch_count": 91}, {"period": 5, "win_rate": 42.86, "avg_win": 6.04, "avg_loss": -5.88, "pl_ratio": 1.0265, "touch_count": 91}, {"period": 10, "win_rate": 42.22, "avg_win": 10.83, "avg_loss": -7.16, "pl_ratio": 1.5123, "touch_count": 90}, {"period": 20, "win_rate": 45.56, "avg_win": 14.53, "avg_loss": -9.33, "pl_ratio": 1.5579, "touch_count": 90}, {"period": 60, "win_rate": 30.34, "avg_win": 39.93, "avg_loss": -14.52, "pl_ratio": 2.7495, "touch_count": 89}, {"period": 126, "win_rate": 47.67, "avg_win": 64.48, "avg_loss": -26.43, "pl_ratio": 2.4401, "touch_count": 86}, {"period": 252, "win_rate": 45.12, "avg_win": 139.42, "avg_loss": -34.97, "pl_ratio": 3.9866, "touch_count": 82}], "L|EMA|50": [{"period": 2, "win_rate": 43.9, "avg_win": 3.94, "avg_loss": -3.43, "pl_ratio": 1.148, "touch_count": 41}, {"period": 3, "win_rate": 46.34, "avg_win": 4.02, "avg_loss": -3.85, "pl_ratio": 1.0451, "touch_count": 41}, {"period": 5, "win_rate": 41.46, "avg_win": 8.71, "avg_loss": -4.8, "pl_ratio": 1.8147, "touch_count": 41}, {"period": 10, "win_rate": 47.5, "avg_win": 11.99, "avg_loss": -6.49, "pl_ratio": 1.8476, "touch_count": 40}, {"period": 20, "win_rate": 50.0, "avg_win": 13.88, "avg_loss": -9.02, "pl_ratio": 1.5399, "touch_count": 40}, {"period": 60, "win_rate": 47.37, "avg_win": 53.26, "avg_loss": -8.93, "pl_ratio": 5.9641, "touch_count": 38}, {"period": 126, "win_rate": 66.67, "avg_win": 130.81, "avg_loss": -18.9, "pl_ratio": 6.923, "touch_count": 36}, {"period": 252, "win_rate": 65.62, "avg_win": 246.93, "avg_loss": -41.39, "pl_ratio": 5.9656, "touch_count": 32}], "S|EMA|50": [{"period": 2, "win_rate": 48.19, "avg_win": 4.94, "avg_loss": -4.06, "pl_ratio": 1.2164, "touch_count": 83}, {"period": 3, "win_rate": 45.78, "avg_win": 5.09, "avg_loss": -3.94, "pl_ratio": 1.2922, "touch_count": 83}, {"period": 5, "win_rate": 40.96, "avg_win": 6.34, "avg_loss": -5.22, "pl_ratio": 1.2144, "touch_count": 83}, {"period": 10, "win_rate": 41.46, "avg_win": 8.26, "avg_loss": -7.35, "pl_ratio": 1.1234, "touch_count": 82}, {"period": 20, "win_rate": 42.68, "avg_win": 9.59, "avg_loss": -9.07, "pl_ratio": 1.0565, "touch_count": 82}, {"period": 60, "win_rate": 29.27, "avg_win": 35.34, "avg_loss": -14.31, "pl_ratio": 2.4698, "touch_count": 82}, {"period": 126, "win_rate": 43.9, "avg_win": 61.17, "avg_loss": -25.65, "pl_ratio": 2.3853, "touch_count": 82}, {"period": 252, "win_rate": 44.44, "avg_win": 137.21, "avg_loss": -33.87, "pl_ratio": 4.0507, "touch_count": 81}], "L|EMA|60": [{"period": 2, "win_rate": 52.38, "avg_win": 4.5, "avg_loss": -3.7, "pl_ratio": 1.2164, "touch_count": 42}, {"period": 3, "win_rate": 52.38, "avg_win": 4.46, "avg_loss": -3.49, "pl_ratio": 1.2781, "touch_count": 42}, {"period": 5, "win_rate": 42.86, "avg_win": 10.04, "avg_loss": -4.55, "pl_ratio": 2.2073, "touch_count": 42}, {"period": 10, "win_rate": 48.78, "avg_win": 17.01, "avg_loss": -6.39, "pl_ratio": 2.6602, "touch_count": 41}, {"period": 20, "win_rate": 46.34, "avg_win": 22.05, "avg_loss": -8.94, "pl_ratio": 2.4677, "touch_count": 41}, {"period": 60, "win_rate": 53.85, "avg_win": 48.39, "avg_loss": -7.77, "pl_ratio": 6.2276, "touch_count": 39}, {"period": 126, "win_rate": 63.89, "avg_win": 123.3, "avg_loss": -17.53, "pl_ratio": 7.0339, "touch_count": 36}, {"period": 252, "win_rate": 57.58, "avg_win": 219.4, "avg_loss": -43.74, "pl_ratio": 5.016, "touch_count": 33}], "S|EMA|60": [{"period": 2, "win_rate": 36.47, "avg_win": 4.18, "avg_loss": -4.71, "pl_ratio": 0.8869, "touch_count": 85}, {"period": 3, "win_rate": 37.65, "avg_win": 4.07, "avg_loss": -4.62, "pl_ratio": 0.8794, "touch_count": 85}, {"period": 5, "win_rate": 28.24, "avg_win": 7.3, "avg_loss": -5.29, "pl_ratio": 1.3808, "touch_count": 85}, {"period": 10, "win_rate": 36.9, "avg_win": 10.1, "avg_loss": -6.93, "pl_ratio": 1.4588, "touch_count": 84}, {"period": 20, "win_rate": 40.48, "avg_win": 10.87, "avg_loss": -9.17, "pl_ratio": 1.1856, "touch_count": 84}, {"period": 60, "win_rate": 28.57, "avg_win": 36.84, "avg_loss": -14.85, "pl_ratio": 2.4809, "touch_count": 84}, {"period": 126, "win_rate": 41.67, "avg_win": 65.15, "avg_loss": -24.43, "pl_ratio": 2.6665, "touch_count": 84}, {"period": 252, "win_rate": 45.24, "avg_win": 130.56, "avg_loss": -33.37, "pl_ratio": 3.913, "touch_count": 84}]}}, "box": {"ticker": "CLYM", "found": true, "vol_data_available": true, "periods_all": {"L": [{"filter": "L", "period": 2, "win_rate": null, "avg_win": null, "avg_loss": null, "pl_ratio": null, "cnt": 0}, {"filter": "L", "period": 3, "win_rate": null, "avg_win": null, "avg_loss": null, "pl_ratio": null, "cnt": 0}, {"filter": "L", "period": 5, "win_rate": null, "avg_win": null, "avg_loss": null, "pl_ratio": null, "cnt": 0}, {"filter": "L", "period": 10, "win_rate": null, "avg_win": null, "avg_loss": null, "pl_ratio": null, "cnt": 0}, {"filter": "L", "period": 20, "win_rate": null, "avg_win": null, "avg_loss": null, "pl_ratio": null, "cnt": 0}, {"filter": "L", "period": 63, "win_rate": null, "avg_win": null, "avg_loss": null, "pl_ratio": null, "cnt": 0}, {"filter": "L", "period": 126, "win_rate": null, "avg_win": null, "avg_loss": null, "pl_ratio": null, "cnt": 0}, {"filter": "L", "period": 252, "win_rate": null, "avg_win": null, "avg_loss": null, "pl_ratio": null, "cnt": 0}], "S": [{"filter": "S", "period": 2, "win_rate": 28.57, "avg_win": 2.34, "avg_loss": -5.35, "pl_ratio": 0.437, "cnt": 7}, {"filter": "S", "period": 3, "win_rate": 28.57, "avg_win": 2.34, "avg_loss": -5.35, "pl_ratio": 0.437, "cnt": 7}, {"filter": "S", "period": 5, "win_rate": 28.57, "avg_win": 2.42, "avg_loss": -5.19, "pl_ratio": 0.4655, "cnt": 7}, {"filter": "S", "period": 10, "win_rate": 57.14, "avg_win": 2.93, "avg_loss": -2.86, "pl_ratio": 1.0247, "cnt": 7}, {"filter": "S", "period": 20, "win_rate": 57.14, "avg_win": 7.1, "avg_loss": -6.2, "pl_ratio": 1.1451, "cnt": 7}, {"filter": "S", "period": 63, "win_rate": 57.14, "avg_win": 35.85, "avg_loss": -11.63, "pl_ratio": 3.0823, "cnt": 7}, {"filter": "S", "period": 126, "win_rate": 57.14, "avg_win": 25.72, "avg_loss": -30.08, "pl_ratio": 0.8552, "cnt": 7}, {"filter": "S", "period": 252, "win_rate": 57.14, "avg_win": 143.46, "avg_loss": -28.15, "pl_ratio": 5.0971, "cnt": 7}]}, "periods_vol2x": {"L": [{"filter": "L", "period": 2, "win_rate": null, "avg_win": null, "avg_loss": null, "pl_ratio": null, "cnt": 0}, {"filter": "L", "period": 3, "win_rate": null, "avg_win": null, "avg_loss": null, "pl_ratio": null, "cnt": 0}, {"filter": "L", "period": 5, "win_rate": null, "avg_win": null, "avg_loss": null, "pl_ratio": null, "cnt": 0}, {"filter": "L", "period": 10, "win_rate": null, "avg_win": null, "avg_loss": null, "pl_ratio": null, "cnt": 0}, {"filter": "L", "period": 20, "win_rate": null, "avg_win": null, "avg_loss": null, "pl_ratio": null, "cnt": 0}, {"filter": "L", "period": 63, "win_rate": null, "avg_win": null, "avg_loss": null, "pl_ratio": null, "cnt": 0}, {"filter": "L", "period": 126, "win_rate": null, "avg_win": null, "avg_loss": null, "pl_ratio": null, "cnt": 0}, {"filter": "L", "period": 252, "win_rate": null, "avg_win": null, "avg_loss": null, "pl_ratio": null, "cnt": 0}], "S": [{"filter": "S", "period": 2, "win_rate": 0.0, "avg_win": 0.0, "avg_loss": -5.33, "pl_ratio": 0.0, "cnt": 2}, {"filter": "S", "period": 3, "win_rate": 0.0, "avg_win": 0.0, "avg_loss": -5.33, "pl_ratio": 0.0, "cnt": 2}, {"filter": "S", "period": 5, "win_rate": 0.0, "avg_win": 0.0, "avg_loss": -6.1, "pl_ratio": 0.0, "cnt": 2}, {"filter": "S", "period": 10, "win_rate": 100.0, "avg_win": 3.33, "avg_loss": null, "pl_ratio": null, "cnt": 2}, {"filter": "S", "period": 20, "win_rate": 100.0, "avg_win": 9.04, "avg_loss": null, "pl_ratio": null, "cnt": 2}, {"filter": "S", "period": 63, "win_rate": 50.0, "avg_win": 48.75, "avg_loss": -26.09, "pl_ratio": 1.8688, "cnt": 2}, {"filter": "S", "period": 126, "win_rate": 50.0, "avg_win": 24.37, "avg_loss": -56.25, "pl_ratio": 0.4333, "cnt": 2}, {"filter": "S", "period": 252, "win_rate": 50.0, "avg_win": 220.0, "avg_loss": -81.25, "pl_ratio": 2.7077, "cnt": 2}]}, "breakout_vol_mult": 2}, "nhigh": {"ticker": "CLYM", "found": true, "market": "US", "last_close": 12.58, "last_date": "2026-07-22", "holds": [2, 3, 5, 10, 20, 60, 126, 252], "entries": {"ATH": {"distance_pct": 127.42, "label": "대기", "breakout_pct": 2.18, "near_pct": null, "days_since_breakout": 2444, "holds": [{"hold": 2, "n": 6, "win_rate": 50.0, "avg_ret": -2.22, "median_ret": -2.26, "avg_win": 9.55, "avg_loss": -13.98, "pl_ratio": 0.6829}, {"hold": 3, "n": 6, "win_rate": 50.0, "avg_ret": -2.22, "median_ret": -2.26, "avg_win": 9.55, "avg_loss": -13.98, "pl_ratio": 0.6829}, {"hold": 5, "n": 6, "win_rate": 33.33, "avg_ret": 0.38, "median_ret": -4.02, "avg_win": 25.37, "avg_loss": -12.11, "pl_ratio": 2.0948}, {"hold": 10, "n": 6, "win_rate": 66.67, "avg_ret": 2.14, "median_ret": 2.53, "avg_win": 13.35, "avg_loss": -20.27, "pl_ratio": 0.6585}, {"hold": 20, "n": 6, "win_rate": 50.0, "avg_ret": -6.41, "median_ret": -5.46, "avg_win": 13.41, "avg_loss": -26.22, "pl_ratio": 0.5114}, {"hold": 60, "n": 6, "win_rate": 0.0, "avg_ret": -37.14, "median_ret": -39.51, "avg_win": 0.0, "avg_loss": -37.14, "pl_ratio": 0.0}, {"hold": 126, "n": 6, "win_rate": 0.0, "avg_ret": -37.8, "median_ret": -39.53, "avg_win": 0.0, "avg_loss": -37.8, "pl_ratio": 0.0}, {"hold": 252, "n": 6, "win_rate": 0.0, "avg_ret": -60.61, "median_ret": -61.25, "avg_win": 0.0, "avg_loss": -60.61, "pl_ratio": 0.0}]}, "20": {"distance_pct": 11.29, "label": "대기", "breakout_pct": 1.3, "near_pct": null, "days_since_breakout": 16, "holds": [{"hold": 2, "n": 150, "win_rate": 42.67, "avg_ret": 0.06, "median_ret": -1.19, "avg_win": 7.0, "avg_loss": -5.1, "pl_ratio": 1.3728}, {"hold": 3, "n": 150, "win_rate": 42.67, "avg_ret": 0.06, "median_ret": -1.19, "avg_win": 7.0, "avg_loss": -5.1, "pl_ratio": 1.3728}, {"hold": 5, "n": 150, "win_rate": 40.0, "avg_ret": 0.56, "median_ret": -1.54, "avg_win": 10.87, "avg_loss": -6.31, "pl_ratio": 1.723}, {"hold": 10, "n": 150, "win_rate": 43.33, "avg_ret": 1.43, "median_ret": -1.29, "avg_win": 15.2, "avg_loss": -9.1, "pl_ratio": 1.6701}, {"hold": 20, "n": 148, "win_rate": 39.19, "avg_ret": -1.03, "median_ret": -3.8, "avg_win": 18.34, "avg_loss": -13.51, "pl_ratio": 1.3574}, {"hold": 60, "n": 141, "win_rate": 36.88, "avg_ret": -1.17, "median_ret": -6.23, "avg_win": 34.86, "avg_loss": -22.23, "pl_ratio": 1.5686}, {"hold": 126, "n": 136, "win_rate": 42.65, "avg_ret": 8.03, "median_ret": -12.51, "avg_win": 65.44, "avg_loss": -34.67, "pl_ratio": 1.8878}, {"hold": 252, "n": 121, "win_rate": 41.32, "avg_ret": 34.04, "median_ret": -18.13, "avg_win": 156.06, "avg_loss": -51.9, "pl_ratio": 3.0072}]}, "55": {"distance_pct": 11.29, "label": "대기", "breakout_pct": 1.3, "near_pct": null, "days_since_breakout": 16, "holds": [{"hold": 2, "n": 89, "win_rate": 46.07, "avg_ret": 0.75, "median_ret": -0.71, "avg_win": 7.48, "avg_loss": -4.99, "pl_ratio": 1.4989}, {"hold": 3, "n": 89, "win_rate": 46.07, "avg_ret": 0.75, "median_ret": -0.71, "avg_win": 7.48, "avg_loss": -4.99, "pl_ratio": 1.4989}, {"hold": 5, "n": 89, "win_rate": 42.7, "avg_ret": 1.79, "median_ret": -1.02, "avg_win": 12.01, "avg_loss": -5.82, "pl_ratio": 2.0648}, {"hold": 10, "n": 89, "win_rate": 46.07, "avg_ret": 2.77, "median_ret": -0.43, "avg_win": 15.91, "avg_loss": -8.44, "pl_ratio": 1.8843}, {"hold": 20, "n": 87, "win_rate": 49.43, "avg_ret": 2.39, "median_ret": -0.35, "avg_win": 17.39, "avg_loss": -12.27, "pl_ratio": 1.4178}, {"hold": 60, "n": 80, "win_rate": 50.0, "avg_ret": 6.4, "median_ret": 0.13, "avg_win": 33.12, "avg_loss": -20.33, "pl_ratio": 1.6294}, {"hold": 126, "n": 76, "win_rate": 56.58, "avg_ret": 19.38, "median_ret": 7.67, "avg_win": 56.38, "avg_loss": -28.84, "pl_ratio": 1.9549}, {"hold": 252, "n": 61, "win_rate": 55.74, "avg_ret": 74.66, "median_ret": 14.53, "avg_win": 168.11, "avg_loss": -43.02, "pl_ratio": 3.9072}]}}, "signal": null}}