{"ma": {"ticker": "MAAS", "found": true, "last_close": 16.5, "last_date": "2026-07-22", "benchmark": "^GSPC", "market_s": true, "ticker_long": true, "ticker_short": true, "mas": [{"ma_type": "SMA", "ma_period": 10, "ma_value": 19.033, "distance_pct": -13.31}, {"ma_type": "SMA", "ma_period": 20, "ma_value": 16.9275, "distance_pct": -2.53}, {"ma_type": "SMA", "ma_period": 30, "ma_value": 16.3533, "distance_pct": 0.9}, {"ma_type": "SMA", "ma_period": 40, "ma_value": 16.174, "distance_pct": 2.02}, {"ma_type": "SMA", "ma_period": 50, "ma_value": 16.489, "distance_pct": 0.07}, {"ma_type": "SMA", "ma_period": 60, "ma_value": 15.8538, "distance_pct": 4.08}, {"ma_type": "EMA", "ma_period": 10, "ma_value": 18.2418, "distance_pct": -9.55}, {"ma_type": "EMA", "ma_period": 21, "ma_value": 17.4031, "distance_pct": -5.19}, {"ma_type": "EMA", "ma_period": 30, "ma_value": 16.9088, "distance_pct": -2.42}, {"ma_type": "EMA", "ma_period": 40, "ma_value": 16.4483, "distance_pct": 0.31}, {"ma_type": "EMA", "ma_period": 50, "ma_value": 16.0215, "distance_pct": 2.99}, {"ma_type": "EMA", "ma_period": 60, "ma_value": 15.6134, "distance_pct": 5.68}], "stats": {"L|SMA|10": [{"period": 2, "win_rate": 39.29, "avg_win": 4.26, "avg_loss": -2.46, "pl_ratio": 1.7332, "touch_count": 112}, {"period": 3, "win_rate": 39.29, "avg_win": 4.24, "avg_loss": -3.25, "pl_ratio": 1.3024, "touch_count": 112}, {"period": 5, "win_rate": 44.14, "avg_win": 4.46, "avg_loss": -4.18, "pl_ratio": 1.0663, "touch_count": 111}, {"period": 10, "win_rate": 46.85, "avg_win": 8.57, "avg_loss": -4.98, "pl_ratio": 1.7202, "touch_count": 111}, {"period": 20, "win_rate": 54.55, "avg_win": 10.98, "avg_loss": -6.52, "pl_ratio": 1.6854, "touch_count": 110}, {"period": 60, "win_rate": 60.19, "avg_win": 19.72, "avg_loss": -11.48, "pl_ratio": 1.7177, "touch_count": 108}, {"period": 126, "win_rate": 51.46, "avg_win": 37.96, "avg_loss": -20.04, "pl_ratio": 1.8946, "touch_count": 103}, {"period": 252, "win_rate": 38.46, "avg_win": 70.87, "avg_loss": -35.3, "pl_ratio": 2.0078, "touch_count": 91}], "S|SMA|10": [{"period": 2, "win_rate": 40.65, "avg_win": 5.0, "avg_loss": -2.95, "pl_ratio": 1.6932, "touch_count": 155}, {"period": 3, "win_rate": 41.94, "avg_win": 5.47, "avg_loss": -3.62, "pl_ratio": 1.5104, "touch_count": 155}, {"period": 5, "win_rate": 44.81, "avg_win": 5.64, "avg_loss": -4.42, "pl_ratio": 1.2773, "touch_count": 154}, {"period": 10, "win_rate": 46.75, "avg_win": 8.81, "avg_loss": -5.45, "pl_ratio": 1.6166, "touch_count": 154}, {"period": 20, "win_rate": 52.29, "avg_win": 11.11, "avg_loss": -7.25, "pl_ratio": 1.5321, "touch_count": 153}, {"period": 60, "win_rate": 59.6, "avg_win": 18.28, "avg_loss": -15.46, "pl_ratio": 1.1821, "touch_count": 151}, {"period": 126, "win_rate": 52.74, "avg_win": 30.21, "avg_loss": -16.47, "pl_ratio": 1.8336, "touch_count": 146}, {"period": 252, "win_rate": 45.65, "avg_win": 67.53, "avg_loss": -28.83, "pl_ratio": 2.3423, "touch_count": 138}], "L|SMA|20": [{"period": 2, "win_rate": 44.44, "avg_win": 3.46, "avg_loss": -3.03, "pl_ratio": 1.1417, "touch_count": 90}, {"period": 3, "win_rate": 43.33, "avg_win": 3.75, "avg_loss": -3.08, "pl_ratio": 1.2182, "touch_count": 90}, {"period": 5, "win_rate": 46.67, "avg_win": 4.34, "avg_loss": -3.31, "pl_ratio": 1.3128, "touch_count": 90}, {"period": 10, "win_rate": 46.67, "avg_win": 6.55, "avg_loss": -3.6, "pl_ratio": 1.8225, "touch_count": 90}, {"period": 20, "win_rate": 57.78, "avg_win": 10.16, "avg_loss": -5.22, "pl_ratio": 1.9464, "touch_count": 90}, {"period": 60, "win_rate": 59.09, "avg_win": 20.1, "avg_loss": -9.27, "pl_ratio": 2.1678, "touch_count": 88}, {"period": 126, "win_rate": 48.19, "avg_win": 34.4, "avg_loss": -22.88, "pl_ratio": 1.5038, "touch_count": 83}, {"period": 252, "win_rate": 36.0, "avg_win": 66.87, "avg_loss": -36.25, "pl_ratio": 1.8445, "touch_count": 75}], "S|SMA|20": [{"period": 2, "win_rate": 46.43, "avg_win": 3.92, "avg_loss": -3.7, "pl_ratio": 1.0584, "touch_count": 112}, {"period": 3, "win_rate": 46.43, "avg_win": 4.24, "avg_loss": -3.76, "pl_ratio": 1.1279, "touch_count": 112}, {"period": 5, "win_rate": 46.43, "avg_win": 5.04, "avg_loss": -4.49, "pl_ratio": 1.1228, "touch_count": 112}, {"period": 10, "win_rate": 43.75, "avg_win": 6.95, "avg_loss": -4.58, "pl_ratio": 1.5179, "touch_count": 112}, {"period": 20, "win_rate": 53.57, "avg_win": 10.16, "avg_loss": -6.07, "pl_ratio": 1.6725, "touch_count": 112}, {"period": 60, "win_rate": 60.0, "avg_win": 18.8, "avg_loss": -14.9, "pl_ratio": 1.2618, "touch_count": 110}, {"period": 126, "win_rate": 56.19, "avg_win": 29.2, "avg_loss": -20.49, "pl_ratio": 1.4251, "touch_count": 105}, {"period": 252, "win_rate": 45.45, "avg_win": 64.87, "avg_loss": -31.98, "pl_ratio": 2.0285, "touch_count": 99}], "L|SMA|30": [{"period": 2, "win_rate": 39.53, "avg_win": 3.39, "avg_loss": -2.0, "pl_ratio": 1.6929, "touch_count": 86}, {"period": 3, "win_rate": 39.53, "avg_win": 3.31, "avg_loss": -2.34, "pl_ratio": 1.4163, "touch_count": 86}, {"period": 5, "win_rate": 48.84, "avg_win": 3.45, "avg_loss": -3.02, "pl_ratio": 1.142, "touch_count": 86}, {"period": 10, "win_rate": 52.33, "avg_win": 7.55, "avg_loss": -3.94, "pl_ratio": 1.9163, "touch_count": 86}, {"period": 20, "win_rate": 52.94, "avg_win": 12.46, "avg_loss": -5.17, "pl_ratio": 2.4118, "touch_count": 85}, {"period": 60, "win_rate": 58.54, "avg_win": 23.93, "avg_loss": -11.93, "pl_ratio": 2.0056, "touch_count": 82}, {"period": 126, "win_rate": 47.44, "avg_win": 39.32, "avg_loss": -22.35, "pl_ratio": 1.7592, "touch_count": 78}, {"period": 252, "win_rate": 36.62, "avg_win": 62.26, "avg_loss": -33.44, "pl_ratio": 1.8618, "touch_count": 71}], "S|SMA|30": [{"period": 2, "win_rate": 47.06, "avg_win": 3.77, "avg_loss": -2.45, "pl_ratio": 1.5374, "touch_count": 102}, {"period": 3, "win_rate": 45.1, "avg_win": 3.79, "avg_loss": -2.83, "pl_ratio": 1.3396, "touch_count": 102}, {"period": 5, "win_rate": 49.02, "avg_win": 3.86, "avg_loss": -3.59, "pl_ratio": 1.0751, "touch_count": 102}, {"period": 10, "win_rate": 51.96, "avg_win": 7.1, "avg_loss": -4.95, "pl_ratio": 1.4343, "touch_count": 102}, {"period": 20, "win_rate": 50.5, "avg_win": 12.17, "avg_loss": -6.3, "pl_ratio": 1.9306, "touch_count": 101}, {"period": 60, "win_rate": 56.12, "avg_win": 22.57, "avg_loss": -13.97, "pl_ratio": 1.6164, "touch_count": 98}, {"period": 126, "win_rate": 54.26, "avg_win": 29.89, "avg_loss": -20.66, "pl_ratio": 1.447, "touch_count": 94}, {"period": 252, "win_rate": 46.67, "avg_win": 68.78, "avg_loss": -31.57, "pl_ratio": 2.1783, "touch_count": 90}], "L|SMA|40": [{"period": 2, "win_rate": 46.07, "avg_win": 3.16, "avg_loss": -2.44, "pl_ratio": 1.2957, "touch_count": 89}, {"period": 3, "win_rate": 44.94, "avg_win": 3.5, "avg_loss": -2.58, "pl_ratio": 1.3565, "touch_count": 89}, {"period": 5, "win_rate": 49.44, "avg_win": 4.1, "avg_loss": -3.12, "pl_ratio": 1.3146, "touch_count": 89}, {"period": 10, "win_rate": 52.81, "avg_win": 8.24, "avg_loss": -3.66, "pl_ratio": 2.2496, "touch_count": 89}, {"period": 20, "win_rate": 56.82, "avg_win": 11.85, "avg_loss": -6.49, "pl_ratio": 1.8253, "touch_count": 88}, {"period": 60, "win_rate": 59.3, "avg_win": 24.91, "avg_loss": -13.55, "pl_ratio": 1.8382, "touch_count": 86}, {"period": 126, "win_rate": 50.6, "avg_win": 43.22, "avg_loss": -23.25, "pl_ratio": 1.859, "touch_count": 83}, {"period": 252, "win_rate": 41.33, "avg_win": 70.8, "avg_loss": -32.16, "pl_ratio": 2.2013, "touch_count": 75}], "S|SMA|40": [{"period": 2, "win_rate": 47.47, "avg_win": 3.77, "avg_loss": -3.04, "pl_ratio": 1.2409, "touch_count": 99}, {"period": 3, "win_rate": 46.46, "avg_win": 4.19, "avg_loss": -3.62, "pl_ratio": 1.1589, "touch_count": 99}, {"period": 5, "win_rate": 47.47, "avg_win": 4.42, "avg_loss": -4.49, "pl_ratio": 0.984, "touch_count": 99}, {"period": 10, "win_rate": 52.53, "avg_win": 8.57, "avg_loss": -5.23, "pl_ratio": 1.639, "touch_count": 99}, {"period": 20, "win_rate": 53.06, "avg_win": 12.89, "avg_loss": -8.18, "pl_ratio": 1.5752, "touch_count": 98}, {"period": 60, "win_rate": 56.25, "avg_win": 24.41, "avg_loss": -14.87, "pl_ratio": 1.6419, "touch_count": 96}, {"period": 126, "win_rate": 56.99, "avg_win": 33.35, "avg_loss": -23.15, "pl_ratio": 1.441, "touch_count": 93}, {"period": 252, "win_rate": 50.0, "avg_win": 75.27, "avg_loss": -30.64, "pl_ratio": 2.457, "touch_count": 88}], "L|SMA|50": [{"period": 2, "win_rate": 43.21, "avg_win": 2.91, "avg_loss": -2.46, "pl_ratio": 1.1843, "touch_count": 81}, {"period": 3, "win_rate": 44.44, "avg_win": 2.84, "avg_loss": -2.61, "pl_ratio": 1.088, "touch_count": 81}, {"period": 5, "win_rate": 53.09, "avg_win": 3.46, "avg_loss": -3.02, "pl_ratio": 1.1434, "touch_count": 81}, {"period": 10, "win_rate": 48.15, "avg_win": 6.78, "avg_loss": -3.7, "pl_ratio": 1.8297, "touch_count": 81}, {"period": 20, "win_rate": 53.09, "avg_win": 10.45, "avg_loss": -5.85, "pl_ratio": 1.7843, "touch_count": 81}, {"period": 60, "win_rate": 53.09, "avg_win": 21.21, "avg_loss": -10.51, "pl_ratio": 2.0169, "touch_count": 81}, {"period": 126, "win_rate": 45.57, "avg_win": 34.82, "avg_loss": -21.43, "pl_ratio": 1.6251, "touch_count": 79}, {"period": 252, "win_rate": 39.73, "avg_win": 53.97, "avg_loss": -27.51, "pl_ratio": 1.9621, "touch_count": 73}], "S|SMA|50": [{"period": 2, "win_rate": 45.65, "avg_win": 4.39, "avg_loss": -3.28, "pl_ratio": 1.3369, "touch_count": 92}, {"period": 3, "win_rate": 46.74, "avg_win": 4.33, "avg_loss": -3.56, "pl_ratio": 1.2182, "touch_count": 92}, {"period": 5, "win_rate": 52.17, "avg_win": 4.49, "avg_loss": -4.54, "pl_ratio": 0.9893, "touch_count": 92}, {"period": 10, "win_rate": 47.83, "avg_win": 8.72, "avg_loss": -4.17, "pl_ratio": 2.0934, "touch_count": 92}, {"period": 20, "win_rate": 54.35, "avg_win": 11.26, "avg_loss": -6.77, "pl_ratio": 1.6638, "touch_count": 92}, {"period": 60, "win_rate": 51.09, "avg_win": 20.35, "avg_loss": -11.41, "pl_ratio": 1.7839, "touch_count": 92}, {"period": 126, "win_rate": 47.78, "avg_win": 30.16, "avg_loss": -19.32, "pl_ratio": 1.5608, "touch_count": 90}, {"period": 252, "win_rate": 47.67, "avg_win": 48.24, "avg_loss": -27.35, "pl_ratio": 1.7637, "touch_count": 86}], "L|SMA|60": [{"period": 2, "win_rate": 46.25, "avg_win": 3.92, "avg_loss": -2.26, "pl_ratio": 1.7394, "touch_count": 80}, {"period": 3, "win_rate": 47.5, "avg_win": 3.64, "avg_loss": -2.27, "pl_ratio": 1.6038, "touch_count": 80}, {"period": 5, "win_rate": 53.75, "avg_win": 5.04, "avg_loss": -3.09, "pl_ratio": 1.6331, "touch_count": 80}, {"period": 10, "win_rate": 46.25, "avg_win": 7.92, "avg_loss": -3.8, "pl_ratio": 2.0847, "touch_count": 80}, {"period": 20, "win_rate": 54.43, "avg_win": 12.77, "avg_loss": -5.9, "pl_ratio": 2.1649, "touch_count": 79}, {"period": 60, "win_rate": 51.32, "avg_win": 15.57, "avg_loss": -10.38, "pl_ratio": 1.4996, "touch_count": 76}, {"period": 126, "win_rate": 42.67, "avg_win": 26.67, "avg_loss": -21.39, "pl_ratio": 1.2468, "touch_count": 75}, {"period": 252, "win_rate": 43.06, "avg_win": 44.76, "avg_loss": -27.7, "pl_ratio": 1.616, "touch_count": 72}], "S|SMA|60": [{"period": 2, "win_rate": 39.76, "avg_win": 3.79, "avg_loss": -3.19, "pl_ratio": 1.1879, "touch_count": 83}, {"period": 3, "win_rate": 40.96, "avg_win": 3.65, "avg_loss": -3.31, "pl_ratio": 1.1016, "touch_count": 83}, {"period": 5, "win_rate": 44.58, "avg_win": 3.83, "avg_loss": -4.79, "pl_ratio": 0.7993, "touch_count": 83}, {"period": 10, "win_rate": 37.35, "avg_win": 9.18, "avg_loss": -4.5, "pl_ratio": 2.0415, "touch_count": 83}, {"period": 20, "win_rate": 49.4, "avg_win": 12.47, "avg_loss": -6.84, "pl_ratio": 1.823, "touch_count": 83}, {"period": 60, "win_rate": 48.19, "avg_win": 18.03, "avg_loss": -11.66, "pl_ratio": 1.5462, "touch_count": 83}, {"period": 126, "win_rate": 50.6, "avg_win": 26.91, "avg_loss": -20.63, "pl_ratio": 1.3042, "touch_count": 83}, {"period": 252, "win_rate": 48.75, "avg_win": 48.91, "avg_loss": -28.5, "pl_ratio": 1.7164, "touch_count": 80}], "L|EMA|10": [{"period": 2, "win_rate": 45.19, "avg_win": 4.1, "avg_loss": -2.89, "pl_ratio": 1.418, "touch_count": 104}, {"period": 3, "win_rate": 43.27, "avg_win": 4.18, "avg_loss": -3.05, "pl_ratio": 1.3692, "touch_count": 104}, {"period": 5, "win_rate": 46.6, "avg_win": 4.66, "avg_loss": -4.46, "pl_ratio": 1.0438, "touch_count": 103}, {"period": 10, "win_rate": 53.4, "avg_win": 8.62, "avg_loss": -5.05, "pl_ratio": 1.7073, "touch_count": 103}, {"period": 20, "win_rate": 63.73, "avg_win": 13.06, "avg_loss": -6.28, "pl_ratio": 2.0796, "touch_count": 102}, {"period": 60, "win_rate": 59.6, "avg_win": 25.43, "avg_loss": -10.91, "pl_ratio": 2.3311, "touch_count": 99}, {"period": 126, "win_rate": 52.81, "avg_win": 39.07, "avg_loss": -18.07, "pl_ratio": 2.1621, "touch_count": 89}, {"period": 252, "win_rate": 46.75, "avg_win": 64.06, "avg_loss": -33.77, "pl_ratio": 1.8968, "touch_count": 77}], "S|EMA|10": [{"period": 2, "win_rate": 43.15, "avg_win": 4.54, "avg_loss": -3.09, "pl_ratio": 1.4697, "touch_count": 146}, {"period": 3, "win_rate": 45.21, "avg_win": 4.43, "avg_loss": -3.72, "pl_ratio": 1.1919, "touch_count": 146}, {"period": 5, "win_rate": 44.14, "avg_win": 4.97, "avg_loss": -4.53, "pl_ratio": 1.0969, "touch_count": 145}, {"period": 10, "win_rate": 46.9, "avg_win": 8.98, "avg_loss": -5.75, "pl_ratio": 1.5611, "touch_count": 145}, {"period": 20, "win_rate": 54.17, "avg_win": 12.73, "avg_loss": -6.76, "pl_ratio": 1.884, "touch_count": 144}, {"period": 60, "win_rate": 58.16, "avg_win": 22.37, "avg_loss": -13.86, "pl_ratio": 1.6148, "touch_count": 141}, {"period": 126, "win_rate": 55.73, "avg_win": 28.44, "avg_loss": -16.26, "pl_ratio": 1.7495, "touch_count": 131}, {"period": 252, "win_rate": 52.42, "avg_win": 62.54, "avg_loss": -28.69, "pl_ratio": 2.1796, "touch_count": 124}], "L|EMA|21": [{"period": 2, "win_rate": 39.33, "avg_win": 4.0, "avg_loss": -3.13, "pl_ratio": 1.2762, "touch_count": 89}, {"period": 3, "win_rate": 39.33, "avg_win": 4.42, "avg_loss": -3.12, "pl_ratio": 1.4168, "touch_count": 89}, {"period": 5, "win_rate": 48.31, "avg_win": 4.22, "avg_loss": -3.04, "pl_ratio": 1.3872, "touch_count": 89}, {"period": 10, "win_rate": 48.31, "avg_win": 7.15, "avg_loss": -3.45, "pl_ratio": 2.0698, "touch_count": 89}, {"period": 20, "win_rate": 60.23, "avg_win": 10.56, "avg_loss": -5.46, "pl_ratio": 1.9343, "touch_count": 88}, {"period": 60, "win_rate": 63.95, "avg_win": 18.51, "avg_loss": -11.89, "pl_ratio": 1.5564, "touch_count": 86}, {"period": 126, "win_rate": 48.78, "avg_win": 36.26, "avg_loss": -19.68, "pl_ratio": 1.8423, "touch_count": 82}, {"period": 252, "win_rate": 36.99, "avg_win": 66.36, "avg_loss": -33.99, "pl_ratio": 1.9525, "touch_count": 73}], "S|EMA|21": [{"period": 2, "win_rate": 45.45, "avg_win": 4.4, "avg_loss": -3.66, "pl_ratio": 1.2035, "touch_count": 121}, {"period": 3, "win_rate": 44.63, "avg_win": 4.46, "avg_loss": -3.61, "pl_ratio": 1.2363, "touch_count": 121}, {"period": 5, "win_rate": 46.28, "avg_win": 4.46, "avg_loss": -4.01, "pl_ratio": 1.1121, "touch_count": 121}, {"period": 10, "win_rate": 46.28, "avg_win": 7.87, "avg_loss": -4.55, "pl_ratio": 1.731, "touch_count": 121}, {"period": 20, "win_rate": 54.17, "avg_win": 11.42, "avg_loss": -6.66, "pl_ratio": 1.7156, "touch_count": 120}, {"period": 60, "win_rate": 63.56, "avg_win": 18.17, "avg_loss": -14.48, "pl_ratio": 1.2552, "touch_count": 118}, {"period": 126, "win_rate": 56.14, "avg_win": 30.66, "avg_loss": -18.29, "pl_ratio": 1.6764, "touch_count": 114}, {"period": 252, "win_rate": 47.66, "avg_win": 64.06, "avg_loss": -28.79, "pl_ratio": 2.2252, "touch_count": 107}], "L|EMA|30": [{"period": 2, "win_rate": 44.32, "avg_win": 3.3, "avg_loss": -2.39, "pl_ratio": 1.3816, "touch_count": 88}, {"period": 3, "win_rate": 45.45, "avg_win": 3.19, "avg_loss": -2.5, "pl_ratio": 1.2776, "touch_count": 88}, {"period": 5, "win_rate": 54.55, "avg_win": 3.59, "avg_loss": -3.02, "pl_ratio": 1.1882, "touch_count": 88}, {"period": 10, "win_rate": 51.14, "avg_win": 7.07, "avg_loss": -3.73, "pl_ratio": 1.8957, "touch_count": 88}, {"period": 20, "win_rate": 62.07, "avg_win": 12.66, "avg_loss": -5.78, "pl_ratio": 2.189, "touch_count": 87}, {"period": 60, "win_rate": 62.35, "avg_win": 25.22, "avg_loss": -11.37, "pl_ratio": 2.2184, "touch_count": 85}, {"period": 126, "win_rate": 47.5, "avg_win": 44.35, "avg_loss": -22.82, "pl_ratio": 1.9432, "touch_count": 80}, {"period": 252, "win_rate": 36.99, "avg_win": 67.16, "avg_loss": -33.95, "pl_ratio": 1.9782, "touch_count": 73}], "S|EMA|30": [{"period": 2, "win_rate": 47.86, "avg_win": 3.85, "avg_loss": -3.06, "pl_ratio": 1.2587, "touch_count": 117}, {"period": 3, "win_rate": 47.86, "avg_win": 3.87, "avg_loss": -3.14, "pl_ratio": 1.2329, "touch_count": 117}, {"period": 5, "win_rate": 48.72, "avg_win": 4.74, "avg_loss": -4.15, "pl_ratio": 1.1435, "touch_count": 117}, {"period": 10, "win_rate": 50.43, "avg_win": 7.91, "avg_loss": -5.88, "pl_ratio": 1.3462, "touch_count": 117}, {"period": 20, "win_rate": 55.17, "avg_win": 13.37, "avg_loss": -8.47, "pl_ratio": 1.5795, "touch_count": 116}, {"period": 60, "win_rate": 58.77, "avg_win": 23.48, "avg_loss": -17.42, "pl_ratio": 1.3479, "touch_count": 114}, {"period": 126, "win_rate": 56.88, "avg_win": 31.9, "avg_loss": -21.07, "pl_ratio": 1.5138, "touch_count": 109}, {"period": 252, "win_rate": 49.04, "avg_win": 67.48, "avg_loss": -30.65, "pl_ratio": 2.2016, "touch_count": 104}], "L|EMA|40": [{"period": 2, "win_rate": 40.7, "avg_win": 3.4, "avg_loss": -2.15, "pl_ratio": 1.5822, "touch_count": 86}, {"period": 3, "win_rate": 40.7, "avg_win": 3.97, "avg_loss": -2.08, "pl_ratio": 1.9076, "touch_count": 86}, {"period": 5, "win_rate": 48.84, "avg_win": 4.46, "avg_loss": -2.89, "pl_ratio": 1.542, "touch_count": 86}, {"period": 10, "win_rate": 48.84, "avg_win": 6.76, "avg_loss": -4.0, "pl_ratio": 1.6882, "touch_count": 86}, {"period": 20, "win_rate": 51.16, "avg_win": 12.91, "avg_loss": -5.89, "pl_ratio": 2.1899, "touch_count": 86}, {"period": 60, "win_rate": 57.65, "avg_win": 21.85, "avg_loss": -11.36, "pl_ratio": 1.923, "touch_count": 85}, {"period": 126, "win_rate": 46.34, "avg_win": 40.58, "avg_loss": -21.61, "pl_ratio": 1.8779, "touch_count": 82}, {"period": 252, "win_rate": 44.0, "avg_win": 64.25, "avg_loss": -28.75, "pl_ratio": 2.2351, "touch_count": 75}], "S|EMA|40": [{"period": 2, "win_rate": 45.19, "avg_win": 4.16, "avg_loss": -2.87, "pl_ratio": 1.451, "touch_count": 104}, {"period": 3, "win_rate": 45.19, "avg_win": 4.55, "avg_loss": -2.98, "pl_ratio": 1.5262, "touch_count": 104}, {"period": 5, "win_rate": 47.12, "avg_win": 5.26, "avg_loss": -4.6, "pl_ratio": 1.143, "touch_count": 104}, {"period": 10, "win_rate": 47.12, "avg_win": 7.78, "avg_loss": -5.45, "pl_ratio": 1.4268, "touch_count": 104}, {"period": 20, "win_rate": 49.04, "avg_win": 14.15, "avg_loss": -7.34, "pl_ratio": 1.9295, "touch_count": 104}, {"period": 60, "win_rate": 52.43, "avg_win": 21.35, "avg_loss": -14.39, "pl_ratio": 1.4839, "touch_count": 103}, {"period": 126, "win_rate": 54.0, "avg_win": 29.93, "avg_loss": -20.9, "pl_ratio": 1.4318, "touch_count": 100}, {"period": 252, "win_rate": 50.53, "avg_win": 57.74, "avg_loss": -26.23, "pl_ratio": 2.2017, "touch_count": 95}], "L|EMA|50": [{"period": 2, "win_rate": 37.97, "avg_win": 2.86, "avg_loss": -1.97, "pl_ratio": 1.4534, "touch_count": 79}, {"period": 3, "win_rate": 37.97, "avg_win": 2.77, "avg_loss": -2.09, "pl_ratio": 1.3202, "touch_count": 79}, {"period": 5, "win_rate": 48.1, "avg_win": 3.71, "avg_loss": -2.89, "pl_ratio": 1.2837, "touch_count": 79}, {"period": 10, "win_rate": 43.04, "avg_win": 6.89, "avg_loss": -3.99, "pl_ratio": 1.7281, "touch_count": 79}, {"period": 20, "win_rate": 51.9, "avg_win": 10.33, "avg_loss": -6.6, "pl_ratio": 1.5659, "touch_count": 79}, {"period": 60, "win_rate": 50.63, "avg_win": 19.39, "avg_loss": -11.59, "pl_ratio": 1.6737, "touch_count": 79}, {"period": 126, "win_rate": 43.59, "avg_win": 42.05, "avg_loss": -20.28, "pl_ratio": 2.073, "touch_count": 78}, {"period": 252, "win_rate": 45.07, "avg_win": 50.03, "avg_loss": -25.05, "pl_ratio": 1.9968, "touch_count": 71}], "S|EMA|50": [{"period": 2, "win_rate": 45.45, "avg_win": 3.94, "avg_loss": -3.72, "pl_ratio": 1.0587, "touch_count": 99}, {"period": 3, "win_rate": 46.46, "avg_win": 4.05, "avg_loss": -3.98, "pl_ratio": 1.0159, "touch_count": 99}, {"period": 5, "win_rate": 48.48, "avg_win": 4.57, "avg_loss": -5.0, "pl_ratio": 0.9151, "touch_count": 99}, {"period": 10, "win_rate": 41.41, "avg_win": 8.07, "avg_loss": -6.32, "pl_ratio": 1.2769, "touch_count": 99}, {"period": 20, "win_rate": 47.47, "avg_win": 12.29, "avg_loss": -8.95, "pl_ratio": 1.3735, "touch_count": 99}, {"period": 60, "win_rate": 47.47, "avg_win": 19.24, "avg_loss": -15.59, "pl_ratio": 1.2339, "touch_count": 99}, {"period": 126, "win_rate": 51.02, "avg_win": 29.51, "avg_loss": -23.23, "pl_ratio": 1.27, "touch_count": 98}, {"period": 252, "win_rate": 50.0, "avg_win": 52.51, "avg_loss": -26.12, "pl_ratio": 2.0103, "touch_count": 94}], "L|EMA|60": [{"period": 2, "win_rate": 50.0, "avg_win": 3.51, "avg_loss": -1.93, "pl_ratio": 1.8163, "touch_count": 78}, {"period": 3, "win_rate": 50.0, "avg_win": 3.3, "avg_loss": -1.91, "pl_ratio": 1.7277, "touch_count": 78}, {"period": 5, "win_rate": 52.56, "avg_win": 4.91, "avg_loss": -2.67, "pl_ratio": 1.8409, "touch_count": 78}, {"period": 10, "win_rate": 55.13, "avg_win": 7.16, "avg_loss": -3.71, "pl_ratio": 1.9292, "touch_count": 78}, {"period": 20, "win_rate": 58.44, "avg_win": 11.2, "avg_loss": -5.71, "pl_ratio": 1.9617, "touch_count": 77}, {"period": 60, "win_rate": 53.95, "avg_win": 18.33, "avg_loss": -10.31, "pl_ratio": 1.7788, "touch_count": 76}, {"period": 126, "win_rate": 45.33, "avg_win": 41.33, "avg_loss": -21.23, "pl_ratio": 1.9471, "touch_count": 75}, {"period": 252, "win_rate": 40.58, "avg_win": 54.3, "avg_loss": -24.78, "pl_ratio": 2.1912, "touch_count": 69}], "S|EMA|60": [{"period": 2, "win_rate": 47.25, "avg_win": 4.24, "avg_loss": -4.11, "pl_ratio": 1.0308, "touch_count": 91}, {"period": 3, "win_rate": 47.25, "avg_win": 4.14, "avg_loss": -4.15, "pl_ratio": 0.9968, "touch_count": 91}, {"period": 5, "win_rate": 47.25, "avg_win": 6.69, "avg_loss": -4.67, "pl_ratio": 1.4319, "touch_count": 91}, {"period": 10, "win_rate": 45.05, "avg_win": 8.32, "avg_loss": -6.35, "pl_ratio": 1.3097, "touch_count": 91}, {"period": 20, "win_rate": 46.15, "avg_win": 13.22, "avg_loss": -8.72, "pl_ratio": 1.5158, "touch_count": 91}, {"period": 60, "win_rate": 51.65, "avg_win": 18.3, "avg_loss": -15.12, "pl_ratio": 1.21, "touch_count": 91}, {"period": 126, "win_rate": 53.85, "avg_win": 26.73, "avg_loss": -22.45, "pl_ratio": 1.1904, "touch_count": 91}, {"period": 252, "win_rate": 52.81, "avg_win": 55.29, "avg_loss": -25.96, "pl_ratio": 2.1301, "touch_count": 89}]}}, "box": {"ticker": "MAAS", "found": true, "vol_data_available": true, "periods_all": {"L": [{"filter": "L", "period": 2, "win_rate": 0.0, "avg_win": 0.0, "avg_loss": -12.02, "pl_ratio": 0.0, "cnt": 2}, {"filter": "L", "period": 3, "win_rate": 0.0, "avg_win": 0.0, "avg_loss": -12.02, "pl_ratio": 0.0, "cnt": 2}, {"filter": "L", "period": 5, "win_rate": 0.0, "avg_win": 0.0, "avg_loss": -11.24, "pl_ratio": 0.0, "cnt": 2}, {"filter": "L", "period": 10, "win_rate": 0.0, "avg_win": 0.0, "avg_loss": -11.04, "pl_ratio": 0.0, "cnt": 2}, {"filter": "L", "period": 20, "win_rate": 0.0, "avg_win": 0.0, "avg_loss": -15.49, "pl_ratio": 0.0, "cnt": 2}, {"filter": "L", "period": 63, "win_rate": 0.0, "avg_win": 0.0, "avg_loss": -11.56, "pl_ratio": 0.0, "cnt": 2}, {"filter": "L", "period": 126, "win_rate": 0.0, "avg_win": 0.0, "avg_loss": -13.74, "pl_ratio": 0.0, "cnt": 2}, {"filter": "L", "period": 252, "win_rate": 0.0, "avg_win": 0.0, "avg_loss": -18.91, "pl_ratio": 0.0, "cnt": 2}], "S": [{"filter": "S", "period": 2, "win_rate": 40.74, "avg_win": 3.64, "avg_loss": -3.6, "pl_ratio": 1.0127, "cnt": 27}, {"filter": "S", "period": 3, "win_rate": 40.74, "avg_win": 3.64, "avg_loss": -3.6, "pl_ratio": 1.0127, "cnt": 27}, {"filter": "S", "period": 5, "win_rate": 40.74, "avg_win": 4.15, "avg_loss": -4.51, "pl_ratio": 0.9205, "cnt": 27}, {"filter": "S", "period": 10, "win_rate": 33.33, "avg_win": 4.33, "avg_loss": -6.03, "pl_ratio": 0.719, "cnt": 27}, {"filter": "S", "period": 20, "win_rate": 44.44, "avg_win": 12.92, "avg_loss": -8.83, "pl_ratio": 1.463, "cnt": 27}, {"filter": "S", "period": 63, "win_rate": 59.26, "avg_win": 19.23, "avg_loss": -18.21, "pl_ratio": 1.0564, "cnt": 27}, {"filter": "S", "period": 126, "win_rate": 48.15, "avg_win": 36.98, "avg_loss": -15.3, "pl_ratio": 2.4174, "cnt": 27}, {"filter": "S", "period": 252, "win_rate": 42.31, "avg_win": 43.43, "avg_loss": -31.29, "pl_ratio": 1.3877, "cnt": 26}]}, "periods_vol2x": {"L": [{"filter": "L", "period": 2, "win_rate": 0.0, "avg_win": 0.0, "avg_loss": -12.02, "pl_ratio": 0.0, "cnt": 2}, {"filter": "L", "period": 3, "win_rate": 0.0, "avg_win": 0.0, "avg_loss": -12.02, "pl_ratio": 0.0, "cnt": 2}, {"filter": "L", "period": 5, "win_rate": 0.0, "avg_win": 0.0, "avg_loss": -11.24, "pl_ratio": 0.0, "cnt": 2}, {"filter": "L", "period": 10, "win_rate": 0.0, "avg_win": 0.0, "avg_loss": -11.04, "pl_ratio": 0.0, "cnt": 2}, {"filter": "L", "period": 20, "win_rate": 0.0, "avg_win": 0.0, "avg_loss": -15.49, "pl_ratio": 0.0, "cnt": 2}, {"filter": "L", "period": 63, "win_rate": 0.0, "avg_win": 0.0, "avg_loss": -11.56, "pl_ratio": 0.0, "cnt": 2}, {"filter": "L", "period": 126, "win_rate": 0.0, "avg_win": 0.0, "avg_loss": -13.74, "pl_ratio": 0.0, "cnt": 2}, {"filter": "L", "period": 252, "win_rate": 0.0, "avg_win": 0.0, "avg_loss": -18.91, "pl_ratio": 0.0, "cnt": 2}], "S": [{"filter": "S", "period": 2, "win_rate": 41.67, "avg_win": 2.06, "avg_loss": -4.44, "pl_ratio": 0.4635, "cnt": 12}, {"filter": "S", "period": 3, "win_rate": 41.67, "avg_win": 2.06, "avg_loss": -4.44, "pl_ratio": 0.4635, "cnt": 12}, {"filter": "S", "period": 5, "win_rate": 50.0, "avg_win": 1.51, "avg_loss": -5.81, "pl_ratio": 0.2604, "cnt": 12}, {"filter": "S", "period": 10, "win_rate": 33.33, "avg_win": 3.99, "avg_loss": -5.85, "pl_ratio": 0.6816, "cnt": 12}, {"filter": "S", "period": 20, "win_rate": 50.0, "avg_win": 18.55, "avg_loss": -7.94, "pl_ratio": 2.3376, "cnt": 12}, {"filter": "S", "period": 63, "win_rate": 75.0, "avg_win": 25.6, "avg_loss": -17.29, "pl_ratio": 1.481, "cnt": 12}, {"filter": "S", "period": 126, "win_rate": 58.33, "avg_win": 54.46, "avg_loss": -11.78, "pl_ratio": 4.6232, "cnt": 12}, {"filter": "S", "period": 252, "win_rate": 27.27, "avg_win": 47.54, "avg_loss": -28.8, "pl_ratio": 1.6506, "cnt": 11}]}, "breakout_vol_mult": 2}, "nhigh": {"ticker": "MAAS", "found": true, "market": "US", "last_close": 16.5, "last_date": "2026-07-22", "holds": [2, 3, 5, 10, 20, 60, 126, 252], "entries": {"ATH": {"distance_pct": 5172.73, "label": "대기", "breakout_pct": 0.49, "near_pct": null, "days_since_breakout": 3494, "holds": [{"hold": 2, "n": 12, "win_rate": 66.67, "avg_ret": 0.14, "median_ret": 1.59, "avg_win": 6.58, "avg_loss": -12.74, "pl_ratio": 0.5162}, {"hold": 3, "n": 12, "win_rate": 66.67, "avg_ret": 0.14, "median_ret": 1.59, "avg_win": 6.58, "avg_loss": -12.74, "pl_ratio": 0.5162}, {"hold": 5, "n": 12, "win_rate": 50.0, "avg_ret": -1.23, "median_ret": -2.13, "avg_win": 14.67, "avg_loss": -17.13, "pl_ratio": 0.8566}, {"hold": 10, "n": 12, "win_rate": 41.67, "avg_ret": -2.72, "median_ret": -9.89, "avg_win": 30.55, "avg_loss": -26.5, "pl_ratio": 1.1532}, {"hold": 20, "n": 12, "win_rate": 25.0, "avg_ret": -12.95, "median_ret": -23.93, "avg_win": 46.58, "avg_loss": -32.8, "pl_ratio": 1.4204}, {"hold": 60, "n": 12, "win_rate": 58.33, "avg_ret": 12.21, "median_ret": 19.96, "avg_win": 47.07, "avg_loss": -36.59, "pl_ratio": 1.2865}, {"hold": 126, "n": 12, "win_rate": 0.0, "avg_ret": -37.01, "median_ret": -33.99, "avg_win": 0.0, "avg_loss": -37.01, "pl_ratio": 0.0}, {"hold": 252, "n": 12, "win_rate": 0.0, "avg_ret": -48.98, "median_ret": -46.02, "avg_win": 0.0, "avg_loss": -48.98, "pl_ratio": 0.0}]}, "20": {"distance_pct": 26.97, "label": "대기", "breakout_pct": 26.2, "near_pct": null, "days_since_breakout": 8, "holds": [{"hold": 2, "n": 219, "win_rate": 40.64, "avg_ret": -0.37, "median_ret": -0.49, "avg_win": 5.57, "avg_loss": -4.43, "pl_ratio": 1.2562}, {"hold": 3, "n": 219, "win_rate": 40.64, "avg_ret": -0.37, "median_ret": -0.49, "avg_win": 5.57, "avg_loss": -4.43, "pl_ratio": 1.2562}, {"hold": 5, "n": 219, "win_rate": 43.38, "avg_ret": -0.27, "median_ret": -0.5, "avg_win": 8.15, "avg_loss": -6.72, "pl_ratio": 1.2128}, {"hold": 10, "n": 218, "win_rate": 38.07, "avg_ret": -0.41, "median_ret": -1.91, "avg_win": 14.59, "avg_loss": -9.63, "pl_ratio": 1.5149}, {"hold": 20, "n": 218, "win_rate": 39.45, "avg_ret": -1.28, "median_ret": -2.55, "avg_win": 16.19, "avg_loss": -12.66, "pl_ratio": 1.2785}, {"hold": 60, "n": 210, "win_rate": 45.71, "avg_ret": 0.33, "median_ret": -1.39, "avg_win": 24.56, "avg_loss": -20.07, "pl_ratio": 1.2237}, {"hold": 126, "n": 204, "win_rate": 44.61, "avg_ret": 3.55, "median_ret": -2.88, "avg_win": 38.33, "avg_loss": -24.47, "pl_ratio": 1.5667}, {"hold": 252, "n": 189, "win_rate": 42.33, "avg_ret": 1.24, "median_ret": -9.76, "avg_win": 60.63, "avg_loss": -42.35, "pl_ratio": 1.4314}]}, "55": {"distance_pct": 28.73, "label": "대기", "breakout_pct": 12.38, "near_pct": null, "days_since_breakout": 40, "holds": [{"hold": 2, "n": 121, "win_rate": 44.63, "avg_ret": -0.43, "median_ret": -0.36, "avg_win": 5.54, "avg_loss": -5.24, "pl_ratio": 1.0576}, {"hold": 3, "n": 121, "win_rate": 44.63, "avg_ret": -0.43, "median_ret": -0.36, "avg_win": 5.54, "avg_loss": -5.24, "pl_ratio": 1.0576}, {"hold": 5, "n": 121, "win_rate": 46.28, "avg_ret": -0.82, "median_ret": -0.47, "avg_win": 7.66, "avg_loss": -8.13, "pl_ratio": 0.9422}, {"hold": 10, "n": 121, "win_rate": 34.71, "avg_ret": -1.88, "median_ret": -2.73, "avg_win": 15.53, "avg_loss": -11.14, "pl_ratio": 1.3941}, {"hold": 20, "n": 121, "win_rate": 34.71, "avg_ret": -3.12, "median_ret": -3.95, "avg_win": 16.43, "avg_loss": -13.52, "pl_ratio": 1.2155}, {"hold": 60, "n": 113, "win_rate": 49.56, "avg_ret": 0.83, "median_ret": -1.15, "avg_win": 23.06, "avg_loss": -21.0, "pl_ratio": 1.0979}, {"hold": 126, "n": 109, "win_rate": 50.46, "avg_ret": 5.21, "median_ret": 0.67, "avg_win": 31.85, "avg_loss": -21.92, "pl_ratio": 1.4529}, {"hold": 252, "n": 100, "win_rate": 45.0, "avg_ret": 7.03, "median_ret": -6.04, "avg_win": 69.26, "avg_loss": -43.88, "pl_ratio": 1.5782}]}}, "signal": null}}